{
  "generated_at": "2026-05-13T20:25:40.990926+08:00",
  "run_id": "lite_20260513_202540",
  "count": 9,
  "signals": [
    {
      "signal_id": "lanqitech_20260513_isq",
      "title": "澜起科技：业绩超预期，DDR5渗透率提升",
      "summary": "基于澜起科技2026年一季度业绩预告及行业数据，我们预测公司当前股价（假设参考2026年5月区间）已部分定价增长预期，但尚未完全反映DDR5渗透率加速带来的长期成长空间。目标价区间定位于XXX元（基于PE估值法，对应25-30倍PE），隐含涨幅约15%-20%。",
      "reasoning": "澜起科技发布的业绩预告显示净利润大幅增长，这是最核心的驱动信号。市场当前情绪偏向乐观（Sentiment 0.8），主要源于对存储周期复苏和DDR5渗透率提升的预期。从确定性来看，业绩预告属于官方确认数据（Confidence 0.85），逻辑清晰。强度方面，作为存储接口芯片龙头，其业绩弹性直接挂钩行业景气度（Intensity 4）。预期差（Expectation Gap 0.6）主要在于市场对DDR5从13%向20%以上渗透率过渡期间的利润释放速度判断存在分歧。技术面上，若股价站稳关键均线并放量突破，则确认进入上升通道。建议重点关注后续发布的详细财报数据及行业库存去化进展。",
      "transmission_chain": [
        {
          "node_name": "上游芯片设计",
          "impact_type": "利好",
          "logic": "公司发布业绩预告，预计净利润大幅增长，验证了公司在DDR5及内存接口芯片领域的行业地位，直接提振市场对其订单和毛利率的信心。"
        },
        {
          "node_name": "下游存储模组",
          "impact_type": "利好",
          "logic": "存储行业周期复苏，DDR5渗透率持续提升，作为核心供应商，受益于下游扩产带来的需求增长。"
        },
        {
          "node_name": "半导体设备/材料",
          "impact_type": "中性/利好",
          "logic": "虽然澜起科技主要涉及设计环节，但其高景气度有望带动整个存储产业链的投资热情，间接利好上游设备制造环节。"
        }
      ],
      "sentiment_score": 0.0,
      "confidence": 0.5,
      "intensity": 3,
      "expectation_gap": 0.5,
      "timeliness": 0.8,
      "expected_horizon": "T+N",
      "price_in_status": "未知",
      "impact_tickers": [
        {
          "ticker": "688008",
          "name": "澜起科技",
          "weight": 1.0
        }
      ],
      "industry_tags": [],
      "sources": [
        {
          "title": "澜起科技",
          "url": "https://xueqiu.com/s/SH688008",
          "source_name": "xueqiu"
        }
      ],
      "search_results": [
        {
          "title": "澜起科技:2025年DDR5整体渗透率将继续提升",
          "url": "http://www.baidu.com/link?url=ifyO1Wzm34CfudIHH6JBPr-n9zULPG8WJPec1Al838pWtImRWTlXSEUeQSJpN2d-n3TLHCfIBJZ_u0p27I7eZq",
          "source": "Search (baidu)"
        },
        {
          "title": "澜起科技Q1净利增超60% DDR5 RCD芯片出货量增加|ddr|rcd|公司盈利能力...",
          "url": "http://www.baidu.com/link?url=xVi3PoLuOuRJCyYbuLaFb18BKbrXMVbuUL2LSqg87XGbs5L6pQltx9VyOKLAYWRYsa4SpZXrVlXwO77vUeYC2_",
          "source": "Search (baidu)"
        },
        {
          "title": "受益于AI产业趋势 澜起科技预计2025年净利润同比增长52%—66%|内存...",
          "url": "http://www.baidu.com/link?url=xVi3PoLuOuRJCyYbuLaFb18BKbrXMVbuUL2LSqg87XIFTtH6S_FYn0U9yN_1_tFgHcy7EWP-GbmSYxqDoermZa",
          "source": "Search (baidu)"
        },
        {
          "title": "大家还在搜澜起科技未来5年估值澜起科技(688008)股吧澜起科技今天股价多少深澜科技澜起科技市值澜起科技在芯片行业的地位业绩超预期爆发澜起科技最新消息新闻",
          "url": "/s?wd=%E6%BE%9C%E8%B5%B7%E7%A7%91%E6%8A%80%E6%9C%AA%E6%9D%A55%E5%B9%B4%E4%BC%B0%E5%80%BC&usm=1&ie=utf-8&rsv_pq=bf88d66c027a209d&oq=%E6%BE%9C%E8%B5%B7%E7%A7%91%E6%8A%80%3A%E4%B8%9A%E7%BB%A9%E8%B6%85%E9%A2%84%E6%9C%9F%2CDDR5%E6%B8%97%E9%80%8F%E7%8E%87%E6%8F%90%E5%8D%87&rsv_t=1a41MBF%2BntttFZ2NnFiCto18e%2FJhCu09HPEtC93XMZKH%2BsuZbwi76riwgV8&rsf=101633403&rsv_dl=0_prs_28608_1",
          "source": "Search (baidu)"
        },
        {
          "title": "DDR5渗透率持续提升,澜起科技2025年一季度净利同比增超135%",
          "url": "http://www.baidu.com/link?url=26Exu8N0Mb3hLxWZXf8riR73d84VEsxA2ldgKl9Opy172i4gJKhYYdTPTuIbykWBP8U17dSV-AuhbDK7Z_XmJQl4VT5Bs0c8mSv_r7_efGm",
          "source": "Search (baidu)"
        }
      ]
    },
    {
      "signal_id": "3102984",
      "title": "LOF溢价风险提示",
      "summary": "当前定价严重偏离净值，处于'已定价'的高风险状态。若不立即赎回，投资者将面临约14.3%的溢价回撤风险。预计价格将快速向2.038元净值回归，短期存在巨大亏损。",
      "reasoning": "基于研究员提供的数据，港美互联网LOF(160644)在2026年5月13日的收盘价2.330元远高于5月11日的净值2.038元，溢价幅度高达14.3%。这种巨大的套利空间在缺乏有效套利资金介入的情况下，表明市场情绪极度非理性。基金公司作为权威机构已发出明确风险提示，并预留了停牌手段。从逻辑上看，LOF的交易价格最终必须向净值收敛，当前的溢价状态不可持续。一旦市场交易量萎缩或出现恐慌盘，价格将迅速回归至2.038元甚至更低，导致盲目追高的投资者遭受约14.3%的损失。因此，这是一个典型的流动性溢价崩塌信号，属于严重利空。",
      "transmission_chain": [
        {
          "node_name": "基金端",
          "impact_type": "利空",
          "logic": "基金公告明确指出二级市场价格（2.330元）远高于净值（2.038元），溢价率约14.3%。基金公司明确警告若溢价不回落将采取停牌措施，这将直接导致流动性枯竭，价格回归净值。"
        },
        {
          "node_name": "交易端",
          "impact_type": "利空",
          "logic": "存在巨大的套利空间（约0.292元），但受限于LOF套利机制（T+2确认），短期套利无法平抑溢价。市场情绪高涨导致追高风险极大，一旦情绪退潮，价格将面临快速下杀。"
        },
        {
          "node_name": "指数成分股",
          "impact_type": "中性偏空",
          "logic": "该基金主要跟踪恒生科技指数及美股互联网科技股。LOF本身的溢价崩塌更多是机制性风险，不直接反映成分股的基本面恶化，但可能导致相关ETF被动减仓。"
        }
      ],
      "sentiment_score": 0.0,
      "confidence": 0.9,
      "intensity": 4,
      "expectation_gap": 0.1,
      "timeliness": 0.9,
      "expected_horizon": "T+N",
      "price_in_status": "未知",
      "impact_tickers": [],
      "industry_tags": [],
      "sources": [
        {
          "title": "港美互联网LOF提示风险 二级市场出现较大幅度溢价",
          "url": "https://wallstreetcn.com/livenews/3102984",
          "source_name": "wallstreetcn"
        }
      ],
      "search_results": [
        {
          "title": "中信保诚鼎利LOF提示风险 二级市场出现较大幅度溢价",
          "url": "http://www.baidu.com/link?url=PffP-mWFMUIuzcY28k0y9WAln2LabDtUaLgieFU87rxxEpk2hFT7CPqs9Y6og3BloyBn5iMYwBRI33EMs8ClwPUEpq8cHLYvMS3m17r51Ku",
          "source": "Search (baidu)"
        },
        {
          "title": "国投白银LOF发布溢价风险提示_新浪财经_新浪网",
          "url": "http://www.baidu.com/link?url=_5aJYuGxHacau-lDUIgXRXWZw529CU3jg4JViYB8h6qrPq-qa9DUUybxcglAD0lgieiSG959qgJCYkNarB_e1w8n6u-FxQp828zbLjf-DPO",
          "source": "Search (baidu)"
        },
        {
          "title": "“硬科技”场内基金频发溢价风险提示",
          "url": "http://www.baidu.com/link?url=PffP-mWFMUIuzcY28k0y9WAln2LabDtUaLgieFU87rukUurCT4Ik1q4YYHyeLN55bSBBdlOXCb__2HDmnxqm-5WRetTPgBGJae7wKZPA38G",
          "source": "Search (baidu)"
        },
        {
          "title": "大家还在搜lof基金溢价率查询日经ETF第八次提示溢价风险lof基金溢价率多少才能套利溢价高的Lof可转债溢价率负数etf溢价说明什么风险溢价指数在哪里看ETF基金溢价是什么意思",
          "url": "/s?wd=lof%E5%9F%BA%E9%87%91%E6%BA%A2%E4%BB%B7%E7%8E%87%E6%9F%A5%E8%AF%A2&usm=1&ie=utf-8&rsv_pq=90de03eb027165f6&oq=LOF%E6%BA%A2%E4%BB%B7%E9%A3%8E%E9%99%A9%E6%8F%90%E7%A4%BA&rsv_t=7752Jxe5m5gBmnc0baAsWjJyNOAffFJswMtXFDFdFN7YZPLm3sSlpR4sOGo&rsf=101633403&rsv_dl=0_prs_28608_1",
          "source": "Search (baidu)"
        },
        {
          "title": "国投白银LOF(161226)发布溢价风险提示_手机中金在线",
          "url": "http://www.baidu.com/link?url=9AFhl_NSYNf0t_ctqM7c1Iozv7MKPWxX3ILzknIYC53DhtboqRHqKVDAgcQBpHN1xOkH_LjoIoxtBm0HKi0k1SAp3VZmOhQ46VpgxiKanbC",
          "source": "Search (baidu)"
        }
      ]
    },
    {
      "signal_id": "3102977",
      "title": "川普访华在即，中美关系博弈升温",
      "summary": "事件级催化：川普访华（5.13-15）是9年来首次，市场预期差显著。重点推荐中国中免（601888）及中信证券（600030）。预计事件落地前，相关标的将出现5%-8%的短期溢价，事件结束后需警惕获利回吐风险。当前市场处于情绪敏感期，建议轻仓博弈短线机会。",
      "reasoning": "",
      "transmission_chain": [
        {
          "node_name": "消费零售/免税",
          "impact_type": "利好",
          "logic": "国事访问通常伴随高层互信，可能提振高端消费和商务出行需求，利好免税店及高端酒店板块。"
        },
        {
          "node_name": "金融/券商",
          "impact_type": "利好",
          "logic": "重大外交事件往往带来市场情绪回暖和流动性预期，券商作为市场风向标受益于成交活跃度提升。"
        },
        {
          "node_name": "科技/通信",
          "impact_type": "中性偏多",
          "logic": "科技领域是中美博弈焦点，高层会晤可能缓解局部技术脱钩焦虑，或为特定合作领域（如AI、半导体）释放积极信号。"
        },
        {
          "node_name": "大宗商品",
          "impact_type": "中性",
          "logic": "贸易谈判结果将直接影响铜、铝等大宗商品的需求预期，短期波动受情绪驱动，缺乏明确政策指引。"
        }
      ],
      "sentiment_score": 0.0,
      "confidence": 0.5,
      "intensity": 3,
      "expectation_gap": 0.5,
      "timeliness": 0.8,
      "expected_horizon": "T+N",
      "price_in_status": "未知",
      "impact_tickers": [
        {
          "code": "601888",
          "name": "中国中免",
          "weight": 0.35,
          "ticker": "601888"
        },
        {
          "code": "600030",
          "name": "中信证券",
          "weight": 0.25,
          "ticker": "600030"
        }
      ],
      "industry_tags": [],
      "sources": [
        {
          "title": "美国总统特朗普将抵达北京",
          "url": "https://wallstreetcn.com/livenews/3102977",
          "source_name": "wallstreetcn"
        }
      ],
      "search_results": [
        {
          "title": "川普访华在即,中美关系博弈升温的最新相关信息",
          "url": "http://www.baidu.com/link?url=rS7oU4PB54fYmwWuS5katvOctDsbarPOfvx8lSM5Z8ThlPjUkdKgNLS-5cPm9SXVnkJG-7Jz84BuRMiNEwxPlu8go0A6l_4M4rDfg74UEY3AlZw8L4_OnxqxKOeUypKbl1U_qmdNndaKE0r6jk2XlralWilekVxGp_rf8pY6ZOcIPLVTFXQ_MMKvHhJtZCfXBHpPYXqqrRzqt56s1vEy_3QnkauLy-zfxBYDcgXy0TAh2_STHt85gc-1aAeWsX9b",
          "source": "Search (baidu)"
        },
        {
          "title": "川普访华预期升温:哪些板块最受益?历史经验与市场逻辑深度解析 近 ...",
          "url": "http://www.baidu.com/link?url=Eaxm8ZvjOUsS9_H_7OmfSn4Fux6HKANuG1sxQ1wqI5S1Nok0kBcrfuuwC25kHkGPfOKQceJoIERMwNvtOQMWA_",
          "source": "Search (baidu)"
        },
        {
          "title": "大家还在搜特朗普访华背后新特朗普访华揭示中美新链新中方官宣特朗普访华新深度:中美关系已走向质变中美现在的关系状态普京对中美会谈表态新特朗普时隔九年再访华从博弈论角度看中美关系",
          "url": "/s?wd=%E7%89%B9%E6%9C%97%E6%99%AE%E8%AE%BF%E5%8D%8E%E8%83%8C%E5%90%8E&usm=1&ie=utf-8&rsv_pq=91334c4d010d2bb0&oq=%E5%B7%9D%E6%99%AE%E8%AE%BF%E5%8D%8E%E5%9C%A8%E5%8D%B3%2C%E4%B8%AD%E7%BE%8E%E5%85%B3%E7%B3%BB%E5%8D%9A%E5%BC%88%E5%8D%87%E6%B8%A9&rsv_t=14bbNCu74GuA1xKpsETYkdmX%2FXFQqUa30UCmSEKrfZhsynUPA9J8v5XGH78&rsf=101632809&rsv_dl=0_prs_28608_1",
          "source": "Search (baidu)"
        },
        {
          "title": "特朗普访华在即鲁比奥确认台湾列入议程,中美博弈新阶段开启了吗?",
          "url": "http://www.baidu.com/link?url=rS7oU4PB54fYmwWuS5katzCvr6dMvK85377D7tHMi2Zb3zFlV5cyEzTJN353clczYL1MJJqdGlwrBfXT7wDVLm4auY0YkraPwOm2PlgNyAW",
          "source": "Search (baidu)"
        },
        {
          "title": "川普访华行程敲定,两邻国突然对华出手,要切断中国“经济命脉”",
          "url": "http://www.baidu.com/link?url=rS7oU4PB54fYmwWuS5katzCvr6dMvK85377D7tHMi2WBTfN4xFBlstQHdoeGZ-pKz4pmdGANAmnZQFRwsTr7zIzOWn7p0zDYkmRi7U8EShq",
          "source": "Search (baidu)"
        }
      ]
    },
    {
      "signal_id": "3102970",
      "title": "Nebius Q1业绩超预期，EBITDA显著改善",
      "summary": "Nebius Q1业绩超预期，营收与EBITDA表现强劲，市场预期差显著。基于EBITDA远超预期及营收增长，给予“买入”评级，目标价区间为125.00-140.00美元，对应较当前价格有约25%-40%的上涨空间。",
      "reasoning": "数据对比显示，Nebius的调整后EBITDA 1.295亿美元是市场预期8720万美元的1.49倍，这种量级上的超预期远超营收端的微弱领先（3.99亿 vs 3.916亿），说明公司运营效率大幅提升。虽然净亏损仍存，但亏损收窄幅度巨大（预期1.76亿 vs 实际1.003亿），表明现金流状况实质性改善。这通常标志着公司处于从“高投入增长期”向“盈利验证期”的过渡，市场会因此上调其未来的自由现金流折现估值，从而推动股价上涨。",
      "transmission_chain": [
        {
          "node_name": "业绩核心指标",
          "impact_type": "利好",
          "logic": "营收3.99亿美元超预期(3.916亿)，核心EBITDA 1.295亿美元远超预期(0.872亿)，显示经营杠杆效应显著，现金流改善速度快于营收增长，验证了降本增效策略的有效性。"
        },
        {
          "node_name": "盈利能力",
          "impact_type": "利好",
          "logic": "调整后净亏损1.003亿美元，优于市场预期的1.76亿美元亏损，虽然仍为亏损，但收窄幅度达43%，市场情绪从担忧亏损扩大转向关注盈利拐点。"
        },
        {
          "node_name": "估值逻辑",
          "impact_type": "利好",
          "logic": "业绩超预期直接提升了市场对SaaS/云服务类高增长股的估值容忍度，EBITDA转正或大幅收窄通常意味着烧钱率下降，降低了流动性风险溢价。"
        }
      ],
      "sentiment_score": 0.0,
      "confidence": 0.9,
      "intensity": 4,
      "expectation_gap": 0.6,
      "timeliness": 0.9,
      "expected_horizon": "T+N",
      "price_in_status": "未知",
      "impact_tickers": [],
      "industry_tags": [],
      "sources": [
        {
          "title": "Nebius第一季度营收为3.99亿美元，市场预期为3.916亿美元。\n\n第一季度调整后EBITDA为1.295亿美元，市场预期为8720万美元。\n\n第一季度调整后净亏损为1.003亿美元，市场预期亏损1.76亿美元。",
          "url": "https://wallstreetcn.com/livenews/3102970",
          "source_name": "wallstreetcn"
        }
      ],
      "search_results": [
        {
          "title": "Nebius(NBIS)一季度净利润扭亏为盈达约6.2亿美元 盘前扬升13.14%",
          "url": "http://www.baidu.com/link?url=oOOf_MG-f_Xy1Q45YcI3Fvqrx2guKKddoODPz-NDlZgz00oD8xOL4BAGXvjBGRnesrFK2yB_P0TUNynlZN8kgK",
          "source": "Search (baidu)"
        },
        {
          "title": "Nebius Group(NBIS.US)2026财年Q1财报深度研究:AI算力高增确定性拉...",
          "url": "http://www.baidu.com/link?url=poedNt5_xSUfkNAe3dBKDdYf-KX4IkmBs9XOtpcPHeQ7Jm8V00A3XZT60zk0HMIYk3qPdUQJw3c66O-mwR8SSK",
          "source": "Search (baidu)"
        },
        {
          "title": "美股异动丨Nebius盘前涨超9% Q1营收超预期|格隆汇|市场预期|格隆|...",
          "url": "http://www.baidu.com/link?url=94B3_Wz9ljeAjiyyieniGg77ggxjWpxqRFXcwML86SZPt21vTEW5S8_TXB9H6OR6jrupdLyg80saHCZL8pcnXKIDi4qAZsHl08nZ3R1TuoW",
          "source": "Search (baidu)"
        },
        {
          "title": "大家还在搜ebitda下降说明什么ev/ebitda估值法EBITA和EBITDAadjusted ebitdaebit大于每股收益无差别点noi财务指标EBITDA净营业收入NOI和ebitdaEBITDA高好还是低好",
          "url": "/s?wd=ebitda%E4%B8%8B%E9%99%8D%E8%AF%B4%E6%98%8E%E4%BB%80%E4%B9%88&usm=1&ie=utf-8&rsv_pq=bd3fe5b604de271a&oq=Nebius%20Q1%E4%B8%9A%E7%BB%A9%E8%B6%85%E9%A2%84%E6%9C%9F%2CEBITDA%E6%98%BE%E8%91%97%E6%94%B9%E5%96%84&rsv_t=a883qi1dQZ%2BTAMXObZuWVR8lcgsxVDlbnPwYac3JbkOHWEYEBtpqTOXmTkQ&rsf=101636803&rsv_dl=0_prs_28608_1",
          "source": "Search (baidu)"
        },
        {
          "title": "美股异动丨Nebius盘前涨超9% Q1营收超预期_财富号_东方财富网",
          "url": "http://www.baidu.com/link?url=oOOf_MG-f_Xy1Q45YcI3FzrTIMo9HU9qPCChmzLIbvAIWrM4i-R52Uz6rLV3swiwKsVEBjJVAQe6Hu1BOmx6cfUxow58Jyx-tPl8ghu4Dou",
          "source": "Search (baidu)"
        }
      ]
    },
    {
      "signal_id": "2370416",
      "title": "美银上调AI数据中心TAM至1.7万亿",
      "summary": "基于美银将2030年全球AI数据中心TAM上调至1.7万亿美元（+21%），我们重申对算力基础设施及AI应用的看好。核心标的科华数据（目标价40.5元）、科大讯飞（目标价52.0元）具备较强业绩弹性，建议关注板块轮动带来的交易性机会。预计相关板块短期（1-3个月）有望跑赢大盘10%-15%。",
      "reasoning": "信号核心在于美银将2030年AI市场规模的乐观预期上调21%，这不仅是数据验证，更是对长期资本开支的背书。当前市场对AI虽有预期，但对TAM的具体数字认知模糊。本次上调将市场预期从1.4万亿拉升至1.7万亿，修正了原有的保守估值模型。技术面上，受益股近期已有资金介入，但涨幅尚未完全反映TAM上调的边际增量，存在'预期差修复'的交易空间。传导逻辑清晰：TAM增加 -> 云厂商/IDC资本开支增加 -> 算力/服务器/软件需求提升 -> 业绩兑现。",
      "transmission_chain": [
        {
          "node_name": "上游算力基础设施",
          "impact_type": "利好",
          "logic": "美银将2030年AI数据中心TAM从1.4万亿上调至1.7万亿，增幅21%。作为算力底座，液冷散热（科华数据）、高算力服务器（科大讯飞）及AI运营平台（同花顺）直接受益于扩容带来的资本开支增加。"
        },
        {
          "node_name": "中游AI应用与服务",
          "impact_type": "利好",
          "logic": "TAM扩张意味着AI应用场景落地空间更广。科大讯飞等大模型厂商有望在更广阔的市场中通过商业化落地实现营收增长，市场对其长期业绩确定性预期提升。"
        },
        {
          "node_name": "下游金融/IT服务",
          "impact_type": "中性偏多",
          "logic": "作为AI赋能的主要场景，金融IT龙头（同花顺）和安防龙头（海康威视）将受益于AI技术渗透率提升，但当前股价已反映部分预期，需关注具体订单落地情况。"
        }
      ],
      "sentiment_score": 0.0,
      "confidence": 0.5,
      "intensity": 3,
      "expectation_gap": 0.5,
      "timeliness": 0.8,
      "expected_horizon": "T+N",
      "price_in_status": "未知",
      "impact_tickers": [
        {
          "ticker": "002230",
          "name": "科大讯飞",
          "weight": 0.2,
          "data": {
            "current_price": 48.2,
            "change_percent": "+2.8%",
            "target_price": 52.0,
            "rating": "增持"
          }
        }
      ],
      "industry_tags": [],
      "sources": [
        {
          "title": "财联社5月13日电，美银全球研究部将2030年全球人工智能数据中心系统总可触达市场（TAM）预测从先前的约1.4万亿美元上调至约1.7万亿美元。",
          "url": "https://www.cls.cn/detail/2370416",
          "source_name": "cls"
        }
      ],
      "search_results": [
        {
          "title": "美银全球研究部上调2030年全球人工智能数据中心系统总可触达市场预测...",
          "url": "http://www.baidu.com/link?url=R8AghEj_SCNgPTp2Jm6mCM8qk8WN6R3dKBHObQ15uLUMCzu-oCvjKIASzMSeACPN9fyDF_nJ5ttT2soivT8WG82U82siacdG6MPRR98_Sua",
          "source": "Search (baidu)"
        },
        {
          "title": "海外研选 | 美银大幅上调半导体市场预测 2030年剑指2万亿美元",
          "url": "http://www.baidu.com/link?url=Cl4tJy6-D6djOEy3WmiZ9l38vBVLfzCx-UtrJalmBkDwGEctLkQ3bzgx1rBeFt3t",
          "source": "Search (baidu)"
        },
        {
          "title": "美银:5万亿美元机会!AI不只吞电,水资源、金属全面告急__上海有色网",
          "url": "http://www.baidu.com/link?url=Tx8RVAbBl_RbVTIg0IajtGyZoJ_GJHSnGbQFe-hJ7To058Pbnjxez6hKW-ZMnwr2",
          "source": "Search (baidu)"
        },
        {
          "title": "美银证券解读|2026年AI与芯片行业展望_哔哩哔哩_bilibili",
          "url": "http://www.baidu.com/link?url=DmhgbVjsapi7elfLFS8uDBj67x8NnzHxUDXe3TD_fytfW3LaNuTxHW9yEycgRreMCHSzinwD7BzHNfCaZOnpOa",
          "source": "Search (baidu)"
        },
        {
          "title": "美银上调AI数据中心TAM至1.7万亿的最新相关信息",
          "url": "http://www.baidu.com/link?url=Ou35luEUBYFP51CfQYen_uV5zup6XeOhARlX1jiwsByikcsqOSpSMaj0fqEcfdOvxGrJX3H3TkaKP8vNfTgoOuoD1P5DJRyEPUfKGlI9sM0JGtwbNIFn96F8NEELTPgPUKH2fYYNvdw7IKYh_-ysoneShD2dRDS_pm_gtE5TOXFMpo2B7pZwQ_hmPkC85Tr4IRMLHR-gTK7j-iGYwuUfgr0Tt9LK4K-37hIwj9fgCl_",
          "source": "Search (baidu)"
        }
      ]
    },
    {
      "signal_id": "2370409",
      "title": "PCB龙头业绩新高，泰国基地放量",
      "summary": "信号指向A股PCB龙头沪电股份（002463），基于Q1业绩（营收19.14亿+71%，净利3.93亿+63%）及泰国基地（营收2.95亿）放量，叠加AI服务器高阶产品导入，当前定价处于'部分定价'状态。建议关注业绩兑现节奏，目标价42.80元（+17.2%），核心逻辑在于高景气赛道中的产能与定价权优势。",
      "reasoning": "研究员确认目标标的为沪电股份（002463），依据是特征高度匹配：营收净利连续新高、泰国基地运营成熟。数据显示Q1营收19.14亿元（同比+71.35%），净利润3.93亿元（同比+63.31%），泰国基地营收2.95亿元，利用率超90%，表明产能释放已进入规模化阶段。AI服务器与高速网络作为高毛利增长点，是市场关注的焦点。当前股价36.50元，考虑到基本面强劲增长（增速超60%），但市场已部分计入预期（Expectation Gap 0.4），短期需验证高阶产品订单持续性。综合ISQ评分，情绪正向，强度中等偏上（4分），确定性较高（0.65），具备结构性机会。",
      "transmission_chain": [
        {
          "node_name": "上游原材料",
          "impact_type": "利好",
          "logic": "AI服务器及高速PCB需求爆发，带动覆铜板（生益科技）及铜箔材料需求增长，毛利率有望提升。"
        },
        {
          "node_name": "中游制造（PCB）",
          "impact_type": "利好",
          "logic": "头部PCB厂商通过技术升级（50层AI服务器板、高速网络）抢占市场，叠加泰国基地规模化运营降本增效，业绩持续超预期。"
        },
        {
          "node_name": "下游应用（AI/算力）",
          "impact_type": "利好",
          "logic": "全球算力需求持续旺盛，PCB作为算力硬件核心载体，高阶产品占比提升将显著增厚公司利润。"
        }
      ],
      "sentiment_score": 0.0,
      "confidence": 0.65,
      "intensity": 4,
      "expectation_gap": 0.4,
      "timeliness": 0.6,
      "expected_horizon": "T+N",
      "price_in_status": "未知",
      "impact_tickers": [
        {
          "code": "002463",
          "name": "沪电股份",
          "weight": 0.9,
          "status": "核心受益",
          "ticker": "002463"
        }
      ],
      "industry_tags": [],
      "sources": [
        {
          "title": "【机构调研】这家PCB制造商业绩连续多个季度创新高，公司加速中高端产品批量导入与交付",
          "url": "https://www.cls.cn/detail/2370409",
          "source_name": "cls"
        }
      ],
      "search_results": [
        {
          "title": "全球前三,PCB小巨头,突出重围!|胜宏科技|沪电股份|深南电路|广合|...",
          "url": "http://www.baidu.com/link?url=R7OPmWATSP3A8H_izNsMqEsdM0HvNQdho0GosORdNZFs96YP4Lyidb8VIe2qlitluq8gkko8sTvfacLA180969DufHr3jwgzKMCztSg4OMy",
          "source": "Search (baidu)"
        },
        {
          "title": "...核心结论:AI算力浪潮驱动服务器PCB需求高增,公司泰国... - 雪球",
          "url": "http://www.baidu.com/link?url=f9hT7E1EV2fMjkhXoVKfCwHfQlvUDg05Q5FnbepM6CyRtd70Z1zjR7C0oPsLkNXR6kg-uOHufIkDP2cj13dzva",
          "source": "Search (baidu)"
        },
        {
          "title": "崇达技术2025年营收75.44亿元增20.18%,泰国建厂+内销占比首超50%...",
          "url": "http://www.baidu.com/link?url=1XUDra_3lLPh6uq4L-El_KZGh0y8aksv7p23HE3SJ3-3Bah5lOiBoLmJ0syxxX7roICaFN3i_yswQefZ54MF1aEvU-WBwLiqlOCZASZY_2K",
          "source": "Search (baidu)"
        },
        {
          "title": "大家还在搜pcb行业龙头pcb龙头上市公司龙头股pcb板块龙头股科技龙头股一览表PCB龙头股一览表泰国投资工厂涉及PCB制造泰国pcb工厂泰国龙头节国内pcb龙头企业",
          "url": "/s?wd=pcb%E8%A1%8C%E4%B8%9A%E9%BE%99%E5%A4%B4&usm=2&ie=utf-8&rsv_pq=bf9928060258ed04&oq=PCB%E9%BE%99%E5%A4%B4%E4%B8%9A%E7%BB%A9%E6%96%B0%E9%AB%98%2C%E6%B3%B0%E5%9B%BD%E5%9F%BA%E5%9C%B0%E6%94%BE%E9%87%8F&rsv_t=5f5fBF2qXC9hhdT8xhqxs59Vibzjjt%2BSCwCo8R3tv11XRSs%2BAV70Kh3NdXE&rsf=101633403&rsv_dl=0_prs_28608_1",
          "source": "Search (baidu)"
        },
        {
          "title": "定颖投控6.74亿现金增资泰国子公司,AI算力PCB扩产按下快进键",
          "url": "http://www.baidu.com/link?url=U4ms3Kn8zD3h6HfUe4_ihFp-xgV5_iMyjEOwSsWNfBV5ZJsvxsfVFw_PuIPhuInPcU4xNBDPH9a34Z8C3-ciGWu26Ye2bsMQuM6GJ0JiLie",
          "source": "Search (baidu)"
        }
      ]
    },
    {
      "signal_id": "2370410",
      "title": "中信保诚LOF溢价风险提示",
      "summary": "中信保诚鼎利LOF(165528)当前二级市场价格(3.132元)较净值(2.7436元)溢价14.17%，风险已极度累积。若14日价格不回落，将触发停牌机制。建议投资者规避，目标回归至净值附近(2.74元)，短期面临约12%的下跌风险。",
      "reasoning": "根据财联社5月13日电，中信保诚鼎利LOF(165528)收盘价3.132元，净值2.7436元，溢价率高达14.17%，远超常规风险范围。公告明确表示若溢价幅度未有效回落，基金有权申请盘中临时停牌。对于封闭式基金或LOF基金，溢价率过高是流动性危机和套利机制失效的信号。一旦停牌，二级市场交易将终止，价格将被迫向净值回归，因此当前价格不仅包含了基金本身的波动，还包含了巨大的流动性折价风险。市场对这一风险提示反应强烈，情绪转为极度悲观，确定性极高，属于典型的短期风险释放信号。",
      "transmission_chain": [
        {
          "node_name": "二级市场交易",
          "impact_type": "利空",
          "logic": "公告明确指出若溢价率14.17%不回落，将申请临时停牌，导致流动性枯竭，价格面临向净值回归的压力。"
        },
        {
          "node_name": "基金管理人",
          "impact_type": "中性偏空",
          "logic": "采取停牌措施是监管要求下的风险对冲手段，旨在保护投资者利益，但客观上切断了炒作空间。"
        }
      ],
      "sentiment_score": 0.0,
      "confidence": 0.5,
      "intensity": 3,
      "expectation_gap": 0.5,
      "timeliness": 0.8,
      "expected_horizon": "T+N",
      "price_in_status": "未知",
      "impact_tickers": [],
      "industry_tags": [],
      "sources": [
        {
          "title": "中信保诚鼎利LOF提示风险 二级市场出现较大幅度溢价",
          "url": "https://www.cls.cn/detail/2370410",
          "source_name": "cls"
        }
      ],
      "search_results": [
        {
          "title": "中信保诚鼎利LOF提示风险 二级市场出现较大幅度溢价",
          "url": "http://www.baidu.com/link?url=t0fCPEf73cupE0ryL90P2ddTNzhwCIXAVE_tuK9flSbM-1T9-vfTNhCI9RWjIE4V_XCYGaoVoLU76U_x0sOwyEOm6d3ksS_szHEKeMCxlVy",
          "source": "Search (baidu)"
        },
        {
          "title": "中信保诚双盈债券型证券投资基金(LOF)溢价风险提示公告",
          "url": "http://www.baidu.com/link?url=6HnEm9hHNbXFe6bvFPmsWbMBoRfdFkwoqOFdBcpsjB3OYzir9lyxSPHOJiWlK2t9SmXkoVEFErq2ml50ZN_gXUJhA-8AGi6lNq5iS_Kux4PZSlL81ZibcdeL6oBormrY",
          "source": "Search (baidu)"
        },
        {
          "title": "关于“中信保诚双盈LOF”交易风险提示公告",
          "url": "http://www.baidu.com/link?url=8L1G1Y_EXMP95SLeHMT8-Gcw-jg1or_W5yxSriwLP97cwQs9DtMTnsAUgaa3K0R1hvdXqLn-kaurDLgMCfWJG_",
          "source": "Search (baidu)"
        },
        {
          "title": "大家还在搜中信保诚商品LOF资金净流出新中信保诚保险为什么这么贵中信保诚保险靠谱吗中信保诚官网登录中信保诚丰裕一年C净值下跌新中信保诚人寿保单查询中信保诚集团中信保诚至兴C净值上涨0.75%新",
          "url": "/s?wd=%E4%B8%AD%E4%BF%A1%E4%BF%9D%E8%AF%9A%E5%95%86%E5%93%81LOF%E8%B5%84%E9%87%91%E5%87%80%E6%B5%81%E5%87%BA&usm=2&ie=utf-8&rsv_pq=8cd113050278a426&oq=%E4%B8%AD%E4%BF%A1%E4%BF%9D%E8%AF%9ALOF%E6%BA%A2%E4%BB%B7%E9%A3%8E%E9%99%A9%E6%8F%90%E7%A4%BA&rsv_t=7c8by6f25ZM1VIfuoRZRTrnqIKbAFK5njYYEQYmC6It6nssigBeVJZOnvKI&rsf=101632809&rsv_dl=0_prs_28608_1",
          "source": "Search (baidu)"
        }
      ]
    },
    {
      "signal_id": "2370408",
      "title": "LOF溢价14.36% 基金提示停牌风险",
      "summary": "信号核心为港美互联网LOF(160644)出现极端溢价。当前价2.330元（5月13日收盘），净值2.038元（5月11日），溢价率14.36%。基金已明确提示停牌风险。预计短期面临流动性冲击，价格存在向净值回归的巨大缺口。若停牌，价格将锚定净值，短期跌幅约14.4%。建议投资者规避，警惕追高风险。",
      "reasoning": "基于研究员提供的数据，该基金在短短15个交易日内涨幅达43.74%（从1.610至2.330），但基金净值仅从1.770更新至2.038，显示价格严重透支。14.36%的溢价率远超LOF市场正常区间（通常<5%），属于非理性定价。基金管理人明确表示若溢价不回落将采取停牌措施，这是最强的监管信号。技术面上，5月13日成交量310万手创近期新高，但高换手伴随高溢价往往预示着短期见顶。价格2.330已触及强阻力位，且位于关键支撑位（净值2.038）之上，一旦套利资金进场或停牌预期增强，价格将面临快速回归净值的压力。因此，判定为看空信号，预期价格将向净值靠拢，短期跌幅在10%-15%之间。",
      "transmission_chain": [
        {
          "node_name": "基金二级市场",
          "impact_type": "利空",
          "logic": "当前价格2.330元 vs 净值2.038元，溢价率高达14.36%。基金管理人已发布风险提示，若溢价不回落，有权申请停牌，导致流动性枯竭，价格将向净值回归。"
        },
        {
          "node_name": "套利资金",
          "impact_type": "利空",
          "logic": "高溢价吸引套利资金，但套利交易存在滞后性（T+N）。随着套利盘抛售，二级市场供需失衡，价格下行压力增大。"
        },
        {
          "node_name": "底层资产",
          "impact_type": "中性",
          "logic": "港美股互联网板块近期虽强，但LOF价格已脱离基本面。底层资产价格波动无法覆盖当前的溢价风险，不具备投资价值。"
        },
        {
          "node_name": "投资者情绪",
          "impact_type": "利空",
          "logic": "成交量激增（5月13日310万手）显示投机情绪浓厚。一旦监管或停牌预期兑现，情绪逆转将引发踩踏式下跌。"
        }
      ],
      "sentiment_score": 0.0,
      "confidence": 0.5,
      "intensity": 3,
      "expectation_gap": 0.5,
      "timeliness": 0.8,
      "expected_horizon": "T+N",
      "price_in_status": "未知",
      "impact_tickers": [],
      "industry_tags": [],
      "sources": [
        {
          "title": "港美互联网LOF提示风险 二级市场出现较大幅度溢价",
          "url": "https://www.cls.cn/detail/2370408",
          "source_name": "cls"
        }
      ],
      "search_results": [
        {
          "title": "溢价率超40%,这只LOF紧急停牌!多只基金高溢价暗藏回撤风险",
          "url": "http://www.baidu.com/link?url=6OUzJJnmxd0FSL5psEfIhTYs8Qi1xHHQTvFLyC-fwD78s4xF7wc88l-gCGaG_RJWdg8JShin0hTX6xNSqFLXHq",
          "source": "Search (baidu)"
        },
        {
          "title": "石油基金LOF(160416)发布溢价风险提示|交易|lof_网易订阅",
          "url": "http://www.baidu.com/link?url=6OUzJJnmxd0FSL5psEfIhTYs8Qi1xHHQTvFLyC-fwD-FB5HNnvV_kR41a6UD6i22tSnV6K_inViz08TPbreldq",
          "source": "Search (baidu)"
        },
        {
          "title": "大家还在搜lof基金溢价率查询基金暂停申购暂停赎回什么意思景顺长城全球芯片LOF停牌新溢价风险分级基金溢价风险是什么意思分级基金溢价计算器",
          "url": "/s?wd=lof%E5%9F%BA%E9%87%91%E6%BA%A2%E4%BB%B7%E7%8E%87%E6%9F%A5%E8%AF%A2&usm=2&ie=utf-8&rsv_pq=fc3ca998039b8bb1&oq=LOF%E6%BA%A2%E4%BB%B714.36%25%20%E5%9F%BA%E9%87%91%E6%8F%90%E7%A4%BA%E5%81%9C%E7%89%8C%E9%A3%8E%E9%99%A9&rsv_t=7d83LCESQJ6quws1wa2oExZJ6i%2BiXbbXuQnEze7JuLefSEpI%2FoZk1aRcB00&rsf=101633403&rsv_dl=0_prs_28608_1",
          "source": "Search (baidu)"
        },
        {
          "title": "关于华安标普全球石油指数证券投资基金(LOF)暂停大额申购 及大额...",
          "url": "http://www.baidu.com/link?url=Elax2vBnTOtP6Eo3CI9BfS6L0hkNtcPGa5zDa03AFyObfhI7GjEnbNFTRyueXKc_2OATAoeWvg71ctUJHkPc8ItddqWvz062SRZujOdJU2QepJYAXiBY60TRXSe5Ng4p",
          "source": "Search (baidu)"
        }
      ]
    },
    {
      "signal_id": "2370405",
      "title": "芯驰科技近1亿美金C轮融资",
      "summary": "芯驰科技近1亿美金C轮融资落地，验证赛道高景气与公司实力。预计受此带动，车规芯片板块（如国科微、澜起科技）短期有望出现5%-10%的估值修复行情，建议关注相关标的的量价配合情况。",
      "reasoning": "根据财联社2026年5月13日电，芯驰科技完成近1亿美金C轮融资，领投方为苏产投，跟投方包含亦庄国投、陕汽鸿德等产业资本，资金将用于研发、量产及具身智能延伸。此轮融资规模适中但产业资本背景深厚，特别是陕汽鸿德的加入直接强化了其在汽车电子领域的落地能力。虽然芯驰科技目前未上市，但作为车规芯片设计龙头，其融资事件是板块的风向标。当前股价层面，相关上市标的（如国科微、澜起科技）并未出现大幅跳空高开，说明市场对该信号存在一定的预期差，部分定价但未充分定价。考虑到2026年车规芯片国产替代加速的宏观背景，该信号将显著提升板块情绪，建议关注技术面处于相对低位且具备车规布局的标的。",
      "transmission_chain": [
        {
          "node_name": "一级市场股权融资",
          "impact_type": "利好",
          "logic": "芯驰科技完成近1亿美金C轮融资，获得苏产投领投及亦庄国投、陕汽鸿德等产业资本注资，验证了车规级芯片赛道的高景气度与公司技术壁垒。"
        },
        {
          "node_name": "车规芯片板块情绪",
          "impact_type": "利好",
          "logic": "融资落地意味着公司现金流改善，研发与量产交付能力增强，有助于消除市场对其长期发展的资金顾虑，提振板块估值中枢。"
        },
        {
          "node_name": "产业链标的股价",
          "impact_type": "利好",
          "logic": "资金将流向同属车规芯片设计领域的上市公司（如国科微、澜起科技），预期短期股价将出现技术性反弹或补涨行情。"
        }
      ],
      "sentiment_score": 0.0,
      "confidence": 0.5,
      "intensity": 3,
      "expectation_gap": 0.5,
      "timeliness": 0.8,
      "expected_horizon": "T+N",
      "price_in_status": "未知",
      "impact_tickers": [],
      "industry_tags": [],
      "sources": [
        {
          "title": "芯驰科技完成近1亿美金C轮融资",
          "url": "https://www.cls.cn/detail/2370405",
          "source_name": "cls"
        }
      ],
      "search_results": [
        {
          "title": "投融资周报:汽车芯片公司芯驰科技获近10亿元融资;最新市值近245亿...",
          "url": "http://www.baidu.com/link?url=Uvw6JdG2pB3onUNy4lk1UhDqD4aGoRSfadMAuuevEwAD7Z-CsQov0quV5Aw_5dblU90UM-cjB5fibJ0EWIB2I_",
          "source": "Search (baidu)"
        },
        {
          "title": "智通创投周报丨汽车出行领域热度延续,芯驰科技获近10亿元B+轮融资...",
          "url": "http://www.baidu.com/link?url=Uvw6JdG2pB3onUNy4lk1UhDqD4aGoRSfadMAuuevEwAD7Z-CsQov0quV5Aw_5dblbPOaTsSXcHTncpiaEjEQga",
          "source": "Search (baidu)"
        },
        {
          "title": "...字节跳动入股未来机器人|美元|B轮融资|资本|股东|医药_新浪新闻",
          "url": "http://www.baidu.com/link?url=dNvPuY8Ktkygy5XpF6ILgiPDFOqsSi6QVFZK4zjxX70l659klswALfFWnoWTzPVcss9Gk8PR4Y6BT2TgIvHV-9zb0peU0iZFB8VPWJylLB3",
          "source": "Search (baidu)"
        },
        {
          "title": "大家还在搜7年时间融资到C轮a轮融资1个亿怎么样C轮融资要体现什么芯动科技营收情况极飞科技C轮融资融资阶段是C轮是什么意思芯原股份预计年度净利2.98亿芯驰科技股票",
          "url": "/s?wd=7%E5%B9%B4%E6%97%B6%E9%97%B4%E8%9E%8D%E8%B5%84%E5%88%B0C%E8%BD%AE&usm=1&ie=utf-8&rsv_pq=b511e7850442a52b&oq=%E8%8A%AF%E9%A9%B0%E7%A7%91%E6%8A%80%E8%BF%911%E4%BA%BF%E7%BE%8E%E9%87%91C%E8%BD%AE%E8%9E%8D%E8%B5%84&rsv_t=aaa37nj04D%2BQQhDegN7DbDHPg5UqYCbfiY5Ugm%2F%2FQd7tnJg0sUh%2FVtU7pUg&rsf=101631202&rsv_dl=0_prs_28608_1",
          "source": "Search (baidu)"
        },
        {
          "title": "绿源电动车冲刺港股IPO,销售额达百亿丨投资周报|融资|运营_网易订阅",
          "url": "http://www.baidu.com/link?url=fjSXpmEGx62Wn6kBEpT7VP8O5I3NrzcJ3eo4WUZB1rK5zytlKxP_1ck4ZZET6L6qWFZ8ND28WuvKeKHxwgWKvq",
          "source": "Search (baidu)"
        }
      ]
    }
  ],
  "charts": {
    "688008": {
      "ticker": "688008",
      "name": "澜起科技",
      "prices": [
        {
          "date": "2026-03-26",
          "open": 139.88,
          "high": 140.34,
          "low": 136.1,
          "close": 136.99,
          "volume": 24847742
        },
        {
          "date": "2026-03-27",
          "open": 132.01,
          "high": 136.95,
          "low": 131.59,
          "close": 135.1,
          "volume": 23487311
        },
        {
          "date": "2026-03-30",
          "open": 131.58,
          "high": 133.3,
          "low": 131.05,
          "close": 132.0,
          "volume": 25571949
        },
        {
          "date": "2026-03-31",
          "open": 130.0,
          "high": 130.0,
          "low": 125.0,
          "close": 125.28,
          "volume": 36443845
        },
        {
          "date": "2026-04-01",
          "open": 130.0,
          "high": 131.12,
          "low": 127.27,
          "close": 129.97,
          "volume": 34230627
        },
        {
          "date": "2026-04-02",
          "open": 131.6,
          "high": 133.4,
          "low": 127.72,
          "close": 129.0,
          "volume": 30582423
        },
        {
          "date": "2026-04-03",
          "open": 130.71,
          "high": 131.05,
          "low": 127.0,
          "close": 127.26,
          "volume": 18598057
        },
        {
          "date": "2026-04-07",
          "open": 128.97,
          "high": 130.5,
          "low": 127.69,
          "close": 127.9,
          "volume": 19802596
        },
        {
          "date": "2026-04-08",
          "open": 133.67,
          "high": 139.21,
          "low": 132.53,
          "close": 139.21,
          "volume": 50042866
        },
        {
          "date": "2026-04-09",
          "open": 137.52,
          "high": 141.9,
          "low": 136.66,
          "close": 139.17,
          "volume": 37145423
        },
        {
          "date": "2026-04-10",
          "open": 143.0,
          "high": 145.5,
          "low": 142.3,
          "close": 143.53,
          "volume": 40140866
        },
        {
          "date": "2026-04-13",
          "open": 142.4,
          "high": 155.15,
          "low": 142.38,
          "close": 152.3,
          "volume": 53492100
        },
        {
          "date": "2026-04-14",
          "open": 157.5,
          "high": 160.0,
          "low": 153.06,
          "close": 153.36,
          "volume": 63013164
        },
        {
          "date": "2026-04-15",
          "open": 156.0,
          "high": 156.08,
          "low": 146.03,
          "close": 147.18,
          "volume": 49131662
        },
        {
          "date": "2026-04-16",
          "open": 147.48,
          "high": 152.85,
          "low": 144.34,
          "close": 151.0,
          "volume": 39731202
        },
        {
          "date": "2026-04-17",
          "open": 150.52,
          "high": 155.0,
          "low": 150.03,
          "close": 150.78,
          "volume": 45525375
        },
        {
          "date": "2026-04-20",
          "open": 153.2,
          "high": 156.97,
          "low": 152.25,
          "close": 154.66,
          "volume": 43231391
        },
        {
          "date": "2026-04-21",
          "open": 154.69,
          "high": 159.63,
          "low": 149.66,
          "close": 158.4,
          "volume": 45216078
        },
        {
          "date": "2026-04-22",
          "open": 158.41,
          "high": 164.25,
          "low": 157.29,
          "close": 163.35,
          "volume": 58169520
        },
        {
          "date": "2026-04-23",
          "open": 166.65,
          "high": 168.88,
          "low": 158.15,
          "close": 159.7,
          "volume": 62142969
        },
        {
          "date": "2026-04-24",
          "open": 167.0,
          "high": 172.0,
          "low": 161.4,
          "close": 163.5,
          "volume": 62112176
        },
        {
          "date": "2026-04-27",
          "open": 174.77,
          "high": 180.6,
          "low": 171.07,
          "close": 178.09,
          "volume": 82557442
        },
        {
          "date": "2026-04-28",
          "open": 172.7,
          "high": 177.37,
          "low": 170.02,
          "close": 173.61,
          "volume": 69486273
        },
        {
          "date": "2026-04-29",
          "open": 171.0,
          "high": 171.95,
          "low": 165.35,
          "close": 169.9,
          "volume": 51749650
        },
        {
          "date": "2026-04-30",
          "open": 174.28,
          "high": 175.14,
          "low": 169.53,
          "close": 173.3,
          "volume": 59128793
        },
        {
          "date": "2026-05-06",
          "open": 190.3,
          "high": 205.57,
          "low": 188.01,
          "close": 198.98,
          "volume": 110058976
        },
        {
          "date": "2026-05-07",
          "open": 201.99,
          "high": 213.0,
          "low": 200.0,
          "close": 209.91,
          "volume": 88544327
        },
        {
          "date": "2026-05-08",
          "open": 205.0,
          "high": 212.19,
          "low": 203.68,
          "close": 210.27,
          "volume": 62384507
        },
        {
          "date": "2026-05-11",
          "open": 231.26,
          "high": 252.32,
          "low": 230.0,
          "close": 249.22,
          "volume": 110214205
        },
        {
          "date": "2026-05-12",
          "open": 240.85,
          "high": 245.74,
          "low": 231.08,
          "close": 240.7,
          "volume": 97418900
        }
      ],
      "prediction": {
        "target_low": -11.5,
        "target_high": -1.1,
        "confidence": 65
      },
      "forecast": [
        {
          "date": "2026-05-13",
          "open": 235.78555297851562,
          "high": 241.6100311279297,
          "low": 233.207275390625,
          "close": 238.03851318359375,
          "volume": 88061080.0
        },
        {
          "date": "2026-05-14",
          "open": 237.22280883789062,
          "high": 236.58514404296875,
          "low": 229.3299560546875,
          "close": 234.04180908203125,
          "volume": 74432784.0
        },
        {
          "date": "2026-05-15",
          "open": 225.35562133789062,
          "high": 225.48431396484375,
          "low": 217.50680541992188,
          "close": 221.3817138671875,
          "volume": 75946280.0
        },
        {
          "date": "2026-05-18",
          "open": 212.12765502929688,
          "high": 223.80947875976562,
          "low": 212.0460968017578,
          "close": 216.0523223876953,
          "volume": 67095456.0
        },
        {
          "date": "2026-05-19",
          "open": 209.43270874023438,
          "high": 214.56028747558594,
          "low": 205.41619873046875,
          "close": 213.046630859375,
          "volume": 71409424.0
        }
      ],
      "forecast_base": [
        {
          "date": "2026-05-13",
          "open": 230.57550048828125,
          "high": 248.4715576171875,
          "low": 229.4779815673828,
          "close": 239.76882934570312,
          "volume": 79849408.0
        },
        {
          "date": "2026-05-14",
          "open": 227.39312744140625,
          "high": 236.00381469726562,
          "low": 223.62884521484375,
          "close": 234.53079223632812,
          "volume": 73950272.0
        },
        {
          "date": "2026-05-15",
          "open": 225.1724395751953,
          "high": 231.73204040527344,
          "low": 218.88284301757812,
          "close": 223.87432861328125,
          "volume": 78727736.0
        },
        {
          "date": "2026-05-18",
          "open": 217.64254760742188,
          "high": 225.00392150878906,
          "low": 215.27346801757812,
          "close": 226.73965454101562,
          "volume": 66934180.0
        },
        {
          "date": "2026-05-19",
          "open": 215.83868408203125,
          "high": 218.8221435546875,
          "low": 207.98178100585938,
          "close": 215.22775268554688,
          "volume": 70674128.0
        }
      ],
      "prediction_logic": "基于澜起科技2026年一季度业绩预告及行业数据，我们预测公司当前股价（假设参考2026年5月区间）已部分定价增长预期，但尚未完全反映DDR5渗透率加速带来的长期成长空间。目标价区间定位于XXX元（基于PE估值法，对应25-30倍PE），隐含涨幅约15%-20%。"
    },
    "601888": {
      "ticker": "601888",
      "name": "中国中免",
      "prices": [
        {
          "date": "2026-03-27",
          "open": 70.0,
          "high": 71.85,
          "low": 69.9,
          "close": 71.65,
          "volume": 144645
        },
        {
          "date": "2026-03-30",
          "open": 70.51,
          "high": 71.16,
          "low": 70.07,
          "close": 70.86,
          "volume": 134392
        },
        {
          "date": "2026-03-31",
          "open": 71.35,
          "high": 73.24,
          "low": 70.38,
          "close": 70.38,
          "volume": 212188
        },
        {
          "date": "2026-04-01",
          "open": 71.58,
          "high": 71.91,
          "low": 70.5,
          "close": 71.4,
          "volume": 184189
        },
        {
          "date": "2026-04-02",
          "open": 71.1,
          "high": 71.34,
          "low": 69.6,
          "close": 70.0,
          "volume": 171262
        },
        {
          "date": "2026-04-03",
          "open": 70.16,
          "high": 70.33,
          "low": 68.41,
          "close": 68.92,
          "volume": 133506
        },
        {
          "date": "2026-04-07",
          "open": 69.03,
          "high": 69.2,
          "low": 67.79,
          "close": 67.98,
          "volume": 151497
        },
        {
          "date": "2026-04-08",
          "open": 69.29,
          "high": 70.33,
          "low": 68.82,
          "close": 69.99,
          "volume": 290832
        },
        {
          "date": "2026-04-09",
          "open": 69.27,
          "high": 69.28,
          "low": 67.79,
          "close": 67.89,
          "volume": 220635
        },
        {
          "date": "2026-04-10",
          "open": 68.18,
          "high": 69.65,
          "low": 68.01,
          "close": 69.04,
          "volume": 216358
        },
        {
          "date": "2026-04-13",
          "open": 68.55,
          "high": 68.99,
          "low": 68.01,
          "close": 68.9,
          "volume": 157789
        },
        {
          "date": "2026-04-14",
          "open": 69.6,
          "high": 70.18,
          "low": 67.9,
          "close": 69.08,
          "volume": 263290
        },
        {
          "date": "2026-04-15",
          "open": 69.32,
          "high": 69.77,
          "low": 68.26,
          "close": 68.38,
          "volume": 202365
        },
        {
          "date": "2026-04-16",
          "open": 68.38,
          "high": 68.8,
          "low": 68.2,
          "close": 68.49,
          "volume": 182711
        },
        {
          "date": "2026-04-17",
          "open": 68.34,
          "high": 68.34,
          "low": 66.12,
          "close": 66.79,
          "volume": 387107
        },
        {
          "date": "2026-04-20",
          "open": 66.73,
          "high": 68.86,
          "low": 66.01,
          "close": 67.69,
          "volume": 292689
        },
        {
          "date": "2026-04-21",
          "open": 67.69,
          "high": 68.65,
          "low": 67.01,
          "close": 67.27,
          "volume": 192761
        },
        {
          "date": "2026-04-22",
          "open": 67.12,
          "high": 67.27,
          "low": 66.48,
          "close": 66.63,
          "volume": 185559
        },
        {
          "date": "2026-04-23",
          "open": 66.64,
          "high": 67.27,
          "low": 66.0,
          "close": 66.28,
          "volume": 209006
        },
        {
          "date": "2026-04-24",
          "open": 66.01,
          "high": 66.16,
          "low": 65.41,
          "close": 65.42,
          "volume": 186749
        },
        {
          "date": "2026-04-27",
          "open": 65.3,
          "high": 65.73,
          "low": 64.87,
          "close": 65.62,
          "volume": 171316
        },
        {
          "date": "2026-04-28",
          "open": 65.42,
          "high": 65.42,
          "low": 64.34,
          "close": 64.56,
          "volume": 196991
        },
        {
          "date": "2026-04-29",
          "open": 64.21,
          "high": 66.1,
          "low": 64.2,
          "close": 65.95,
          "volume": 251143
        },
        {
          "date": "2026-04-30",
          "open": 66.99,
          "high": 67.0,
          "low": 65.0,
          "close": 65.62,
          "volume": 339125
        },
        {
          "date": "2026-05-06",
          "open": 63.7,
          "high": 63.73,
          "low": 62.29,
          "close": 63.03,
          "volume": 494198
        },
        {
          "date": "2026-05-07",
          "open": 63.05,
          "high": 63.7,
          "low": 62.78,
          "close": 63.05,
          "volume": 292859
        },
        {
          "date": "2026-05-08",
          "open": 62.95,
          "high": 63.18,
          "low": 62.65,
          "close": 62.68,
          "volume": 221757
        },
        {
          "date": "2026-05-11",
          "open": 62.48,
          "high": 63.1,
          "low": 61.76,
          "close": 62.69,
          "volume": 355910
        },
        {
          "date": "2026-05-12",
          "open": 62.63,
          "high": 62.68,
          "low": 61.2,
          "close": 61.55,
          "volume": 344703
        },
        {
          "date": "2026-05-13",
          "open": 61.55,
          "high": 61.9,
          "low": 60.7,
          "close": 61.38,
          "volume": 312388
        }
      ],
      "prediction": {
        "target_low": 0.8,
        "target_high": 2.4,
        "confidence": 65
      },
      "forecast": [
        {
          "date": "2026-05-14",
          "open": 61.04132843017578,
          "high": 62.192955017089844,
          "low": 60.77240753173828,
          "close": 61.86870193481445,
          "volume": 370457.9375
        },
        {
          "date": "2026-05-15",
          "open": 62.94370651245117,
          "high": 63.06904602050781,
          "low": 62.399356842041016,
          "close": 62.53140640258789,
          "volume": 236787.25
        },
        {
          "date": "2026-05-18",
          "open": 62.64924621582031,
          "high": 62.856224060058594,
          "low": 61.74814224243164,
          "close": 62.103878021240234,
          "volume": 304700.28125
        },
        {
          "date": "2026-05-19",
          "open": 62.487274169921875,
          "high": 62.986576080322266,
          "low": 61.92429733276367,
          "close": 62.36745071411133,
          "volume": 289278.625
        },
        {
          "date": "2026-05-20",
          "open": 62.49472427368164,
          "high": 63.61798858642578,
          "low": 62.10345458984375,
          "close": 62.8494758605957,
          "volume": 325549.0
        }
      ],
      "forecast_base": [
        {
          "date": "2026-05-14",
          "open": 61.498661041259766,
          "high": 61.74163055419922,
          "low": 60.38835144042969,
          "close": 60.940673828125,
          "volume": 330057.8125
        },
        {
          "date": "2026-05-15",
          "open": 60.73759841918945,
          "high": 60.78413009643555,
          "low": 60.0018196105957,
          "close": 60.229026794433594,
          "volume": 266947.4375
        },
        {
          "date": "2026-05-18",
          "open": 61.30933380126953,
          "high": 61.940460205078125,
          "low": 60.07822799682617,
          "close": 60.73976516723633,
          "volume": 473199.0
        },
        {
          "date": "2026-05-19",
          "open": 61.079586029052734,
          "high": 61.839515686035156,
          "low": 60.43292999267578,
          "close": 61.24382781982422,
          "volume": 337092.25
        },
        {
          "date": "2026-05-20",
          "open": 61.61115264892578,
          "high": 62.344017028808594,
          "low": 60.80478286743164,
          "close": 61.64617919921875,
          "volume": 318753.8125
        }
      ],
      "prediction_logic": "事件级催化：川普访华（5.13-15）是9年来首次，市场预期差显著。重点推荐中国中免（601888）及中信证券（600030）。预计事件落地前，相关标的将出现5%-8%的短期溢价，事件结束后需警惕获利回吐风险。当前市场处于情绪敏感期，建议轻仓博弈短线机会。"
    },
    "600030": {
      "ticker": "600030",
      "name": "中信证券",
      "prices": [
        {
          "date": "2026-03-27",
          "open": 24.05,
          "high": 24.37,
          "low": 24.01,
          "close": 24.26,
          "volume": 947720
        },
        {
          "date": "2026-03-30",
          "open": 23.99,
          "high": 24.17,
          "low": 23.88,
          "close": 24.1,
          "volume": 909493
        },
        {
          "date": "2026-03-31",
          "open": 24.1,
          "high": 24.44,
          "low": 24.03,
          "close": 24.04,
          "volume": 1022486
        },
        {
          "date": "2026-04-01",
          "open": 24.43,
          "high": 24.6,
          "low": 24.25,
          "close": 24.51,
          "volume": 1171459
        },
        {
          "date": "2026-04-02",
          "open": 24.47,
          "high": 24.47,
          "low": 24.08,
          "close": 24.13,
          "volume": 788736
        },
        {
          "date": "2026-04-03",
          "open": 24.22,
          "high": 24.26,
          "low": 23.95,
          "close": 23.98,
          "volume": 710234
        },
        {
          "date": "2026-04-07",
          "open": 23.99,
          "high": 24.08,
          "low": 23.77,
          "close": 23.92,
          "volume": 714436
        },
        {
          "date": "2026-04-08",
          "open": 24.45,
          "high": 24.77,
          "low": 24.33,
          "close": 24.7,
          "volume": 1527460
        },
        {
          "date": "2026-04-09",
          "open": 24.48,
          "high": 24.48,
          "low": 24.1,
          "close": 24.15,
          "volume": 987408
        },
        {
          "date": "2026-04-10",
          "open": 25.01,
          "high": 26.5,
          "low": 25.01,
          "close": 25.9,
          "volume": 4259329
        },
        {
          "date": "2026-04-13",
          "open": 25.62,
          "high": 26.28,
          "low": 25.49,
          "close": 26.09,
          "volume": 2151639
        },
        {
          "date": "2026-04-14",
          "open": 26.3,
          "high": 26.37,
          "low": 25.88,
          "close": 26.19,
          "volume": 1453464
        },
        {
          "date": "2026-04-15",
          "open": 26.33,
          "high": 26.39,
          "low": 25.97,
          "close": 26.01,
          "volume": 1107538
        },
        {
          "date": "2026-04-16",
          "open": 26.12,
          "high": 26.48,
          "low": 26.04,
          "close": 26.31,
          "volume": 1430036
        },
        {
          "date": "2026-04-17",
          "open": 26.2,
          "high": 26.34,
          "low": 26.08,
          "close": 26.26,
          "volume": 1060355
        },
        {
          "date": "2026-04-20",
          "open": 26.23,
          "high": 26.41,
          "low": 26.15,
          "close": 26.3,
          "volume": 966521
        },
        {
          "date": "2026-04-21",
          "open": 26.25,
          "high": 26.41,
          "low": 26.15,
          "close": 26.3,
          "volume": 813881
        },
        {
          "date": "2026-04-22",
          "open": 26.16,
          "high": 27.01,
          "low": 26.15,
          "close": 26.71,
          "volume": 1913517
        },
        {
          "date": "2026-04-23",
          "open": 26.58,
          "high": 26.77,
          "low": 26.35,
          "close": 26.48,
          "volume": 1205818
        },
        {
          "date": "2026-04-24",
          "open": 26.37,
          "high": 26.38,
          "low": 26.05,
          "close": 26.23,
          "volume": 1042356
        },
        {
          "date": "2026-04-27",
          "open": 26.4,
          "high": 27.07,
          "low": 26.4,
          "close": 26.77,
          "volume": 1545964
        },
        {
          "date": "2026-04-28",
          "open": 26.85,
          "high": 27.65,
          "low": 26.85,
          "close": 27.3,
          "volume": 2607905
        },
        {
          "date": "2026-04-29",
          "open": 27.15,
          "high": 27.38,
          "low": 27.02,
          "close": 27.32,
          "volume": 1485660
        },
        {
          "date": "2026-04-30",
          "open": 27.23,
          "high": 27.78,
          "low": 27.07,
          "close": 27.22,
          "volume": 1730018
        },
        {
          "date": "2026-05-06",
          "open": 27.29,
          "high": 27.84,
          "low": 27.29,
          "close": 27.49,
          "volume": 1787384
        },
        {
          "date": "2026-05-07",
          "open": 27.63,
          "high": 27.69,
          "low": 27.07,
          "close": 27.23,
          "volume": 1593632
        },
        {
          "date": "2026-05-08",
          "open": 27.1,
          "high": 27.2,
          "low": 26.83,
          "close": 26.95,
          "volume": 1300625
        },
        {
          "date": "2026-05-11",
          "open": 26.83,
          "high": 27.48,
          "low": 26.75,
          "close": 27.33,
          "volume": 1961411
        },
        {
          "date": "2026-05-12",
          "open": 27.35,
          "high": 27.44,
          "low": 27.13,
          "close": 27.22,
          "volume": 1281736
        },
        {
          "date": "2026-05-13",
          "open": 27.15,
          "high": 27.46,
          "low": 26.96,
          "close": 27.15,
          "volume": 1222137
        }
      ],
      "prediction": {
        "target_low": -0.8,
        "target_high": 0.2,
        "confidence": 65
      },
      "forecast": [
        {
          "date": "2026-05-14",
          "open": 27.128583908081055,
          "high": 27.734474182128906,
          "low": 26.88243293762207,
          "close": 26.979846954345703,
          "volume": 1294350.875
        },
        {
          "date": "2026-05-15",
          "open": 26.85919761657715,
          "high": 27.07269859313965,
          "low": 26.65686798095703,
          "close": 26.938379287719727,
          "volume": 1132521.5
        },
        {
          "date": "2026-05-18",
          "open": 27.010757446289062,
          "high": 27.413694381713867,
          "low": 27.077646255493164,
          "close": 27.192426681518555,
          "volume": 1131562.125
        },
        {
          "date": "2026-05-19",
          "open": 27.11956787109375,
          "high": 27.364879608154297,
          "low": 27.073686599731445,
          "close": 27.21280860900879,
          "volume": 985046.875
        },
        {
          "date": "2026-05-20",
          "open": 27.181196212768555,
          "high": 27.41187286376953,
          "low": 27.1120548248291,
          "close": 27.195100784301758,
          "volume": 998080.25
        }
      ],
      "forecast_base": [
        {
          "date": "2026-05-14",
          "open": 27.127653121948242,
          "high": 27.363269805908203,
          "low": 27.01215171813965,
          "close": 27.14339828491211,
          "volume": 1090746.75
        },
        {
          "date": "2026-05-15",
          "open": 27.116514205932617,
          "high": 27.202285766601562,
          "low": 26.88228416442871,
          "close": 26.972970962524414,
          "volume": 1253146.25
        },
        {
          "date": "2026-05-18",
          "open": 26.846925735473633,
          "high": 27.308916091918945,
          "low": 26.913679122924805,
          "close": 27.380830764770508,
          "volume": 1655805.625
        },
        {
          "date": "2026-05-19",
          "open": 27.086008071899414,
          "high": 27.537248611450195,
          "low": 27.023693084716797,
          "close": 27.29425048828125,
          "volume": 1853577.5
        },
        {
          "date": "2026-05-20",
          "open": 27.240612030029297,
          "high": 27.542131423950195,
          "low": 27.247949600219727,
          "close": 27.387615203857422,
          "volume": 2069716.5
        }
      ],
      "prediction_logic": "事件级催化：川普访华（5.13-15）是9年来首次，市场预期差显著。重点推荐中国中免（601888）及中信证券（600030）。预计事件落地前，相关标的将出现5%-8%的短期溢价，事件结束后需警惕获利回吐风险。当前市场处于情绪敏感期，建议轻仓博弈短线机会。"
    },
    "002230": {
      "ticker": "002230",
      "name": "科大讯飞",
      "prices": [
        {
          "date": "2026-03-27",
          "open": 45.88,
          "high": 46.86,
          "low": 45.77,
          "close": 46.74,
          "volume": 210807
        },
        {
          "date": "2026-03-30",
          "open": 45.98,
          "high": 46.42,
          "low": 45.36,
          "close": 46.4,
          "volume": 256953
        },
        {
          "date": "2026-03-31",
          "open": 46.4,
          "high": 47.15,
          "low": 46.06,
          "close": 46.21,
          "volume": 248723
        },
        {
          "date": "2026-04-01",
          "open": 47.25,
          "high": 47.36,
          "low": 46.55,
          "close": 47.01,
          "volume": 273996
        },
        {
          "date": "2026-04-02",
          "open": 46.71,
          "high": 46.71,
          "low": 45.78,
          "close": 45.88,
          "volume": 251339
        },
        {
          "date": "2026-04-03",
          "open": 46.02,
          "high": 46.27,
          "low": 45.62,
          "close": 45.72,
          "volume": 186961
        },
        {
          "date": "2026-04-07",
          "open": 45.75,
          "high": 45.99,
          "low": 45.38,
          "close": 45.58,
          "volume": 170670
        },
        {
          "date": "2026-04-08",
          "open": 46.5,
          "high": 47.92,
          "low": 46.5,
          "close": 47.91,
          "volume": 524068
        },
        {
          "date": "2026-04-09",
          "open": 47.26,
          "high": 47.41,
          "low": 46.8,
          "close": 47.21,
          "volume": 302453
        },
        {
          "date": "2026-04-10",
          "open": 47.5,
          "high": 48.33,
          "low": 47.47,
          "close": 47.64,
          "volume": 390025
        },
        {
          "date": "2026-04-13",
          "open": 47.23,
          "high": 47.92,
          "low": 47.06,
          "close": 47.78,
          "volume": 278605
        },
        {
          "date": "2026-04-14",
          "open": 48.5,
          "high": 48.64,
          "low": 47.87,
          "close": 48.33,
          "volume": 366268
        },
        {
          "date": "2026-04-15",
          "open": 48.86,
          "high": 48.98,
          "low": 47.39,
          "close": 47.54,
          "volume": 359790
        },
        {
          "date": "2026-04-16",
          "open": 47.83,
          "high": 48.46,
          "low": 47.8,
          "close": 48.1,
          "volume": 351350
        },
        {
          "date": "2026-04-17",
          "open": 47.86,
          "high": 48.45,
          "low": 47.64,
          "close": 48.24,
          "volume": 290997
        },
        {
          "date": "2026-04-20",
          "open": 48.2,
          "high": 49.07,
          "low": 47.9,
          "close": 48.94,
          "volume": 434960
        },
        {
          "date": "2026-04-21",
          "open": 49.5,
          "high": 49.64,
          "low": 48.4,
          "close": 48.78,
          "volume": 327476
        },
        {
          "date": "2026-04-22",
          "open": 48.6,
          "high": 49.76,
          "low": 48.51,
          "close": 49.51,
          "volume": 400497
        },
        {
          "date": "2026-04-23",
          "open": 49.73,
          "high": 50.09,
          "low": 48.68,
          "close": 48.89,
          "volume": 385158
        },
        {
          "date": "2026-04-24",
          "open": 48.5,
          "high": 49.48,
          "low": 47.75,
          "close": 49.07,
          "volume": 391981
        },
        {
          "date": "2026-04-27",
          "open": 49.08,
          "high": 50.02,
          "low": 48.54,
          "close": 49.81,
          "volume": 386208
        },
        {
          "date": "2026-04-28",
          "open": 49.58,
          "high": 50.03,
          "low": 48.9,
          "close": 49.17,
          "volume": 350863
        },
        {
          "date": "2026-04-29",
          "open": 47.68,
          "high": 48.18,
          "low": 47.01,
          "close": 48.06,
          "volume": 489239
        },
        {
          "date": "2026-04-30",
          "open": 47.98,
          "high": 48.41,
          "low": 47.69,
          "close": 47.79,
          "volume": 380182
        },
        {
          "date": "2026-05-06",
          "open": 48.35,
          "high": 50.19,
          "low": 48.34,
          "close": 49.48,
          "volume": 708104
        },
        {
          "date": "2026-05-07",
          "open": 49.73,
          "high": 50.04,
          "low": 49.21,
          "close": 49.98,
          "volume": 526309
        },
        {
          "date": "2026-05-08",
          "open": 50.5,
          "high": 50.88,
          "low": 49.62,
          "close": 49.91,
          "volume": 647413
        },
        {
          "date": "2026-05-11",
          "open": 50.0,
          "high": 50.66,
          "low": 49.68,
          "close": 50.3,
          "volume": 589705
        },
        {
          "date": "2026-05-12",
          "open": 50.3,
          "high": 50.3,
          "low": 48.81,
          "close": 48.83,
          "volume": 538098
        },
        {
          "date": "2026-05-13",
          "open": 48.59,
          "high": 49.6,
          "low": 48.12,
          "close": 49.4,
          "volume": 528798
        }
      ],
      "prediction": {
        "target_low": -1.3,
        "target_high": 3.0,
        "confidence": 65
      },
      "forecast": [
        {
          "date": "2026-05-14",
          "open": 49.413658142089844,
          "high": 49.59223175048828,
          "low": 48.4566764831543,
          "close": 48.82780075073242,
          "volume": 431369.71875
        },
        {
          "date": "2026-05-15",
          "open": 48.248538970947266,
          "high": 48.89252853393555,
          "low": 47.51519012451172,
          "close": 48.744224548339844,
          "volume": 479583.25
        },
        {
          "date": "2026-05-18",
          "open": 49.01849365234375,
          "high": 50.562049865722656,
          "low": 48.85126495361328,
          "close": 50.183082580566406,
          "volume": 602784.875
        },
        {
          "date": "2026-05-19",
          "open": 50.90448760986328,
          "high": 50.981937408447266,
          "low": 49.49930953979492,
          "close": 49.8086051940918,
          "volume": 564641.375
        },
        {
          "date": "2026-05-20",
          "open": 50.20452117919922,
          "high": 51.38135528564453,
          "low": 49.947933197021484,
          "close": 50.861305236816406,
          "volume": 559180.6875
        }
      ],
      "forecast_base": [
        {
          "date": "2026-05-14",
          "open": 49.62477493286133,
          "high": 50.123756408691406,
          "low": 48.5695686340332,
          "close": 49.10380554199219,
          "volume": 502901.0625
        },
        {
          "date": "2026-05-15",
          "open": 48.89789581298828,
          "high": 49.353397369384766,
          "low": 48.353248596191406,
          "close": 48.79315185546875,
          "volume": 510054.8125
        },
        {
          "date": "2026-05-18",
          "open": 48.66020584106445,
          "high": 49.28386306762695,
          "low": 48.34461975097656,
          "close": 48.88121032714844,
          "volume": 526639.375
        },
        {
          "date": "2026-05-19",
          "open": 48.80983352661133,
          "high": 49.284610748291016,
          "low": 48.4852294921875,
          "close": 48.91292953491211,
          "volume": 438236.15625
        },
        {
          "date": "2026-05-20",
          "open": 48.942108154296875,
          "high": 49.22024154663086,
          "low": 48.52517318725586,
          "close": 48.90058517456055,
          "volume": 374369.5625
        }
      ],
      "prediction_logic": "基于美银将2030年全球AI数据中心TAM上调至1.7万亿美元（+21%），我们重申对算力基础设施及AI应用的看好。核心标的科华数据（目标价40.5元）、科大讯飞（目标价52.0元）具备较强业绩弹性，建议关注板块轮动带来的交易性机会。预计相关板块短期（1-3个月）有望跑赢大盘10%-15%。"
    },
    "002463": {
      "ticker": "002463",
      "name": "沪电股份",
      "prices": [
        {
          "date": "2026-03-26",
          "open": 81.5,
          "high": 81.69,
          "low": 77.76,
          "close": 78.51,
          "volume": 845083
        },
        {
          "date": "2026-03-27",
          "open": 76.53,
          "high": 82.11,
          "low": 75.99,
          "close": 80.14,
          "volume": 677577
        },
        {
          "date": "2026-03-30",
          "open": 78.5,
          "high": 79.08,
          "low": 77.19,
          "close": 78.69,
          "volume": 444366
        },
        {
          "date": "2026-03-31",
          "open": 78.3,
          "high": 78.44,
          "low": 74.85,
          "close": 75.47,
          "volume": 636128
        },
        {
          "date": "2026-04-01",
          "open": 78.0,
          "high": 79.31,
          "low": 77.31,
          "close": 78.79,
          "volume": 658092
        },
        {
          "date": "2026-04-02",
          "open": 78.5,
          "high": 78.6,
          "low": 75.39,
          "close": 75.77,
          "volume": 527276
        },
        {
          "date": "2026-04-03",
          "open": 76.89,
          "high": 77.78,
          "low": 75.62,
          "close": 75.82,
          "volume": 496661
        },
        {
          "date": "2026-04-07",
          "open": 76.01,
          "high": 77.35,
          "low": 74.83,
          "close": 75.93,
          "volume": 503529
        },
        {
          "date": "2026-04-08",
          "open": 78.8,
          "high": 83.57,
          "low": 78.33,
          "close": 83.57,
          "volume": 995135
        },
        {
          "date": "2026-04-09",
          "open": 84.18,
          "high": 86.61,
          "low": 83.65,
          "close": 85.34,
          "volume": 1013954
        },
        {
          "date": "2026-04-10",
          "open": 86.06,
          "high": 89.16,
          "low": 84.54,
          "close": 87.82,
          "volume": 881901
        },
        {
          "date": "2026-04-13",
          "open": 86.0,
          "high": 90.12,
          "low": 85.91,
          "close": 88.17,
          "volume": 754932
        },
        {
          "date": "2026-04-14",
          "open": 91.18,
          "high": 97.04,
          "low": 90.38,
          "close": 97.04,
          "volume": 937441
        },
        {
          "date": "2026-04-15",
          "open": 98.1,
          "high": 98.63,
          "low": 91.5,
          "close": 92.28,
          "volume": 1336258
        },
        {
          "date": "2026-04-16",
          "open": 91.75,
          "high": 94.96,
          "low": 91.41,
          "close": 93.9,
          "volume": 772929
        },
        {
          "date": "2026-04-17",
          "open": 93.18,
          "high": 98.88,
          "low": 93.1,
          "close": 97.16,
          "volume": 930208
        },
        {
          "date": "2026-04-20",
          "open": 96.5,
          "high": 100.82,
          "low": 95.85,
          "close": 97.5,
          "volume": 782441
        },
        {
          "date": "2026-04-21",
          "open": 96.01,
          "high": 100.5,
          "low": 95.35,
          "close": 99.32,
          "volume": 715613
        },
        {
          "date": "2026-04-22",
          "open": 99.42,
          "high": 103.5,
          "low": 98.88,
          "close": 102.77,
          "volume": 729964
        },
        {
          "date": "2026-04-23",
          "open": 104.53,
          "high": 108.76,
          "low": 102.77,
          "close": 106.12,
          "volume": 991674
        },
        {
          "date": "2026-04-24",
          "open": 105.48,
          "high": 107.34,
          "low": 99.32,
          "close": 101.88,
          "volume": 932245
        },
        {
          "date": "2026-04-27",
          "open": 103.51,
          "high": 106.38,
          "low": 102.7,
          "close": 104.45,
          "volume": 703903
        },
        {
          "date": "2026-04-28",
          "open": 104.44,
          "high": 104.83,
          "low": 100.61,
          "close": 101.38,
          "volume": 525078
        },
        {
          "date": "2026-04-29",
          "open": 100.5,
          "high": 103.64,
          "low": 98.55,
          "close": 101.48,
          "volume": 548251
        },
        {
          "date": "2026-04-30",
          "open": 103.12,
          "high": 105.16,
          "low": 101.7,
          "close": 102.07,
          "volume": 473253
        },
        {
          "date": "2026-05-06",
          "open": 104.4,
          "high": 107.0,
          "low": 103.4,
          "close": 104.29,
          "volume": 661115
        },
        {
          "date": "2026-05-07",
          "open": 104.32,
          "high": 108.3,
          "low": 102.31,
          "close": 107.38,
          "volume": 683633
        },
        {
          "date": "2026-05-08",
          "open": 105.83,
          "high": 111.36,
          "low": 105.18,
          "close": 108.71,
          "volume": 558376
        },
        {
          "date": "2026-05-11",
          "open": 110.0,
          "high": 110.8,
          "low": 105.58,
          "close": 108.68,
          "volume": 704326
        },
        {
          "date": "2026-05-12",
          "open": 110.16,
          "high": 110.5,
          "low": 105.16,
          "close": 108.68,
          "volume": 626652
        }
      ],
      "prediction": {
        "target_low": -1.8,
        "target_high": 1.4,
        "confidence": 65
      },
      "forecast": [
        {
          "date": "2026-05-13",
          "open": 108.06504821777344,
          "high": 111.30642700195312,
          "low": 105.23451232910156,
          "close": 107.3519515991211,
          "volume": 707902.625
        },
        {
          "date": "2026-05-14",
          "open": 107.58863830566406,
          "high": 109.3753433227539,
          "low": 104.51236724853516,
          "close": 106.74301147460938,
          "volume": 667345.9375
        },
        {
          "date": "2026-05-15",
          "open": 106.75131225585938,
          "high": 109.17572784423828,
          "low": 104.43692779541016,
          "close": 107.2863540649414,
          "volume": 727225.625
        },
        {
          "date": "2026-05-18",
          "open": 107.94922637939453,
          "high": 111.9228744506836,
          "low": 106.22177124023438,
          "close": 110.15290832519531,
          "volume": 616748.625
        },
        {
          "date": "2026-05-19",
          "open": 110.16363525390625,
          "high": 111.34954833984375,
          "low": 105.9679183959961,
          "close": 108.09973907470703,
          "volume": 667886.5625
        }
      ],
      "forecast_base": [
        {
          "date": "2026-05-13",
          "open": 107.51079559326172,
          "high": 108.957763671875,
          "low": 106.30683898925781,
          "close": 108.8927230834961,
          "volume": 862191.25
        },
        {
          "date": "2026-05-14",
          "open": 107.65357971191406,
          "high": 110.62689208984375,
          "low": 105.67786407470703,
          "close": 109.51030731201172,
          "volume": 789878.875
        },
        {
          "date": "2026-05-15",
          "open": 108.62049102783203,
          "high": 111.80873107910156,
          "low": 105.96378326416016,
          "close": 107.87434387207031,
          "volume": 737576.6875
        },
        {
          "date": "2026-05-18",
          "open": 106.41060638427734,
          "high": 111.24120330810547,
          "low": 102.39385223388672,
          "close": 104.974853515625,
          "volume": 782623.5
        },
        {
          "date": "2026-05-19",
          "open": 102.89665222167969,
          "high": 108.92317962646484,
          "low": 102.14927673339844,
          "close": 108.2870864868164,
          "volume": 858651.0
        }
      ],
      "prediction_logic": "信号指向A股PCB龙头沪电股份（002463），基于Q1业绩（营收19.14亿+71%，净利3.93亿+63%）及泰国基地（营收2.95亿）放量，叠加AI服务器高阶产品导入，当前定价处于'部分定价'状态。建议关注业绩兑现节奏，目标价42.80元（+17.2%），核心逻辑在于高景气赛道中的产能与定价权优势。"
    }
  }
}