{
  "generated_at": "2026-03-31T01:09:03.421797+08:00",
  "run_id": "lite_20260331_010903",
  "count": 1,
  "signals": [
    {
      "signal_id": "2329706",
      "title": "哥伦比亚失业率低于预期，利好拉美资源出口",
      "summary": "哥伦比亚2月失业率意外降至9.2%（预期9.4%），经济数据边际改善。该信号对能源板块（石油、石化）影响权重最高，预计利好相关上市公司的出口订单预期，提振板块情绪。",
      "reasoning": "哥伦比亚作为拉美主要经济体，其失业率数据的走低（9.2% vs 9.4%）通常意味着劳动力市场趋紧，反映经济活动活跃，这将直接带动当地对能源、原材料及工业品的进口需求。基于传导逻辑，该利好主要利好中国对哥伦比亚的能源出口。考虑到当前时间节点（2026年3月底），市场已对宏观复苏有一定定价，但该数据提供了新的边际验证。因此，逻辑上该信号属于中强度利好，预期差适中，主要利好传统能源板块，对电子板块影响较弱。",
      "transmission_chain": [
        {
          "node_name": "宏观事件",
          "impact_type": "利好",
          "logic": "哥伦比亚失业率9.2%低于预期9.4%，显示当地经济活动活跃，需求端有边际改善迹象，有利于大宗商品进口需求。"
        },
        {
          "node_name": "能源化工",
          "impact_type": "利好",
          "logic": "作为南美主要经济体，经济复苏预期将提振对原油及石化产品的消费，利好中国油气出口企业营收预期。"
        },
        {
          "node_name": "电子设备",
          "impact_type": "中性偏多",
          "logic": "经济活跃度提升可能带动拉美地区半导体设备与软件的采购需求，但直接关联度相对较弱。"
        }
      ],
      "sentiment_score": 0.0,
      "confidence": 0.5,
      "intensity": 3,
      "expectation_gap": 0.5,
      "timeliness": 0.8,
      "expected_horizon": "T+N",
      "price_in_status": "未知",
      "impact_tickers": [],
      "industry_tags": [],
      "sources": [
        {
          "title": "财联社3月31日电，哥伦比亚2月份失业率为9.2%，预期为9.4%。",
          "url": "https://www.cls.cn/detail/2329706",
          "source_name": "cls"
        }
      ],
      "search_results": [
        {
          "title": "2025年上半年哥伦比亚各地区失业率全面下降",
          "url": "http://www.baidu.com/link?url=5BdKZEC61eyBEK6D1DvySojkeEPOJ3kMxJeLtPKFbsvuQK2xkg_7QxqhkNhxi3DPqtPrCGDqlRIG--Hjf8u5w9-klLDTnx1l8WgpJfVIAsLhcmMMPSSAXS4YRJLdn4SZ",
          "source": "Search (baidu)"
        },
        {
          "title": "哥伦比亚 12 月全国失业率为 9.1%,这一数据透露了哪些信息? - 知乎",
          "url": "http://www.baidu.com/link?url=iSuFgkFMxk6HwazUZJNpLOuBidL_fxt_eAqNGxn7rNyXVAMMoVMY_ALA9MJJ0FBJOrjwweM_YvSCEWwBYXY3svlJzvg8RA-8OkNOv4BPGPe",
          "source": "Search (baidu)"
        },
        {
          "title": "76%进入智利的中资企业实现盈利,拉美如何成为中企出海的下一个蓝海",
          "url": "http://www.baidu.com/link?url=FUgqgKF9fLxImWgAhzC5Dww4YByVLevsGH4_PYtuZMDvdsWvPElp413Y9OTqzJByrUXxaTn9TrbjikqsZyq7AitDVs46I8vzjKpDieZlwJi",
          "source": "Search (baidu)"
        },
        {
          "title": "大家还在搜哥伦比亚经济经济增长与失业率的关系哥伦比亚国家经济怎么样哥伦比亚属于拉丁美洲吗哥伦比亚经济发达吗南非失业率哥伦比亚矿产资源哥伦比亚的经济状况",
          "url": "/s?wd=%E5%93%A5%E4%BC%A6%E6%AF%94%E4%BA%9A%E7%BB%8F%E6%B5%8E&ie=utf-8&rsv_pq=d38a163f000e2a4d&oq=%E5%93%A5%E4%BC%A6%E6%AF%94%E4%BA%9A%E5%A4%B1%E4%B8%9A%E7%8E%87%E4%BD%8E%E4%BA%8E%E9%A2%84%E6%9C%9F%2C%E5%88%A9%E5%A5%BD%E6%8B%89%E7%BE%8E%E8%B5%84%E6%BA%90%E5%87%BA%E5%8F%A3&rsv_t=ff27oK2SkD3gAJq7d8efGB5qX7esnCbZCUvS1hupLX8tx8NMNF0s968Jezc&rsf=101633403&rsv_dl=0_prs_28608_1",
          "source": "Search (baidu)"
        },
        {
          "title": "【惠誉评论】美国“门罗主义”回潮推升拉美、中资资产风险",
          "url": "http://www.baidu.com/link?url=_dXqcHvUdyCWtSrJG-04yLSN7DONFAeiMpDNr7YjzPRpzrA6ItAT_PDrIEPwxYlCznjZqOFrlYcZqWIt3-tPNb2qo-8jMTtrTiENsqSpyoi",
          "source": "Search (baidu)"
        }
      ]
    }
  ],
  "charts": {}
}