{
  "generated_at": "2026-03-09T19:38:31.113307+08:00",
  "run_id": "lite_20260309_193831",
  "count": 4,
  "signals": [
    {
      "signal_id": "SH600938",
      "title": "地缘政治致油价涨，海油30日涨27%超预期",
      "summary": "基于研究员提供的数据，中国海油当前股价43.36元，30日涨幅27.19%，处于强势上涨后的高位震荡阶段（最高44.54元）。尽管涨幅显著，但地缘政治导致的原油供给收缩逻辑尚未完全定价。短期关注44.54元阻力位，若突破可看至48-50元区间（+10%至+15%）；若遇阻回调，支撑位在41.60元附近（+4.5%）。建议关注3月10日开盘竞价及后续量能变化。",
      "reasoning": "根据研究员提供的数据，中国海油(600938)在3月2日放量涨停至39.46元，随后在3月9日收盘报43.36元，30日累计涨幅达27.19%。当前价格43.36元已接近30日高点44.54元，显示多头力量强劲，技术面处于相对高位。核心驱动因素为地缘政治导致的原油供给收缩（俄罗斯减产50万桶/日）及国内经济复苏带来的需求预期。虽然股价已大幅上涨，但考虑到油价上涨带来的业绩弹性以及市场对能源安全主题的持续关注，当前定价仍存在一定预期差。股价在44.54元附近面临技术阻力，若能放量突破，有望打开进一步上涨空间；反之，若量能不足，可能面临短期回调风险。综合判断，当前信号强度为4，情绪偏向乐观，市场对地缘政治带来的供给冲击反应积极。",
      "transmission_chain": [
        {
          "node_name": "地缘政治与供给端",
          "impact_type": "利好",
          "logic": "俄罗斯3月起削减50万桶/日供应，叠加地缘冲突升级，市场预期原油供给收缩，推动布伦特/WTI油价上涨。"
        },
        {
          "node_name": "上游油气开采",
          "impact_type": "利好",
          "logic": "油价上涨直接提升中国海油的原油销售价格和产量贡献，增强公司业绩弹性和毛利率。"
        },
        {
          "node_name": "市场情绪与估值",
          "impact_type": "利好",
          "logic": "股价30日涨幅27.19%，突破前期震荡区间（39.46元），主力资金在3月2日放量1772万手后持续介入，市场对能源安全和国企估值重塑预期强烈。"
        }
      ],
      "sentiment_score": 0.0,
      "confidence": 0.5,
      "intensity": 3,
      "expectation_gap": 0.5,
      "timeliness": 0.8,
      "expected_horizon": "T+N",
      "price_in_status": "未知",
      "impact_tickers": [
        {
          "code": "600938",
          "name": "中国海油",
          "weight": 1.0,
          "ticker": "600938"
        }
      ],
      "industry_tags": [],
      "sources": [
        {
          "title": "中国海油",
          "url": "https://xueqiu.com/s/SH600938",
          "source_name": "xueqiu"
        }
      ],
      "search_results": [
        {
          "title": "三桶油集体涨停背后:地缘政治如何牵动全球油价神经?",
          "url": "http://www.baidu.com/link?url=9i8bmugAn68vsWwOugvbR21ROEBpl2ujTk0KCENBSU-cIdSBaqZhDANHHEOZiD64RgzM2VPWqTJTaizxxXjab2eweUny8xF0Y7wOCpH6ZOu",
          "source": "Search (baidu)"
        },
        {
          "title": "三桶油罕见集体涨停背后:地缘政治如何操控油价心跳?",
          "url": "http://www.baidu.com/link?url=9i8bmugAn68vsWwOugvbR21ROEBpl2ujTk0KCENBSU-cIdSBaqZhDANHHEOZiD64mDJYXtl6O_XIQd5k2kMUJJeMi8PB1uMMumSWztmVjcy",
          "source": "Search (baidu)"
        },
        {
          "title": "地缘政治致油价涨,海油30日涨27%超预期 - 视频大全 - 高清在线观看",
          "url": "/sf/vsearch?pd=video&wd=%E5%9C%B0%E7%BC%98%E6%94%BF%E6%B2%BB%E8%87%B4%E6%B2%B9%E4%BB%B7%E6%B6%A8%2C%E6%B5%B7%E6%B2%B930%E6%97%A5%E6%B6%A827%25%E8%B6%85%E9%A2%84%E6%9C%9F&tn=vsearch&lid=c4a15c3e0012275a&ie=utf-8&rsv_pq=c4a15c3e0012275a&rsv_spt=5&rsv_bp=1&f=8&atn=index",
          "source": "Search (baidu)"
        },
        {
          "title": "大家还在搜油价大涨最新消息下周油价会上涨吗海油为什么比石油便宜中国海油海油发展油价持续上涨油价或将大幅下调原因中海油今日油价石油还会继续上涨吗海油",
          "url": "/s?wd=%E6%B2%B9%E4%BB%B7%E5%A4%A7%E6%B6%A8%E6%9C%80%E6%96%B0%E6%B6%88%E6%81%AF&usm=1&ie=utf-8&rsv_pq=c4a15c3e0012275a&oq=%E5%9C%B0%E7%BC%98%E6%94%BF%E6%B2%BB%E8%87%B4%E6%B2%B9%E4%BB%B7%E6%B6%A8%2C%E6%B5%B7%E6%B2%B930%E6%97%A5%E6%B6%A827%25%E8%B6%85%E9%A2%84%E6%9C%9F&rsv_t=828eqi3ykH6NMBFB9iE8fOy5%2FOiwVMQQrqdd2d1FriW5SVNvWwit2%2B9PxxA&rsf=101636803&rsv_dl=0_prs_28608_1",
          "source": "Search (baidu)"
        },
        {
          "title": "中石化、中海油、中石油集体提示风险 地缘政治引爆油价涨停潮...",
          "url": "http://www.baidu.com/link?url=cHjpynT2EVNd1nksLt1GCM4T627SC5_6hRZDrw4ZjmcLJC9hK27qFJGv1-SmRFcJXyZQg1R-08Q19siEzMlLN7l8nZsfJA0UZvq94ErxygK",
          "source": "Search (baidu)"
        }
      ]
    },
    {
      "signal_id": "SH688158",
      "title": "优刻得-W放量突破20日均线",
      "summary": "优刻得-W (688158) 今日强势反攻，股价从低点33.99元累计反弹28.12%，现价45.38元逼近前期高点45.80元。短期目标位看向50.00元（突破阻力位），对应区间涨幅约10%-15%。建议关注20日均线(37.80)的支撑有效性及量能持续性。若回踩支撑位企稳，则上行空间打开。",
      "reasoning": "",
      "transmission_chain": [
        {
          "node_name": "AI智能体+云服务",
          "impact_type": "利好",
          "logic": "市场将公司归类至AI智能体及Open Claw细分赛道，叠加云计算基础设施需求，引发资金对AI算力底座及智能体应用场景的重新估值。"
        },
        {
          "node_name": "技术面突破",
          "impact_type": "利好",
          "logic": "股价放量突破20日均线(37.80)及前期震荡平台，日涨幅19.99%且换手率16.84%，显示主力资金强势介入，市场情绪由观望转为看多。"
        },
        {
          "node_name": "资金博弈",
          "impact_type": "中性偏多",
          "logic": "高换手率伴随股价急涨，虽显示筹码活跃，但也意味着短期获利盘增加，存在震荡消化浮筹的可能。"
        }
      ],
      "sentiment_score": 0.0,
      "confidence": 0.7,
      "intensity": 4,
      "expectation_gap": 0.4,
      "timeliness": 0.75,
      "expected_horizon": "T+N",
      "price_in_status": "未知",
      "impact_tickers": [
        {
          "code": "688158",
          "name": "优刻得-W",
          "weight": 1.0,
          "ticker": "688158"
        }
      ],
      "industry_tags": [],
      "sources": [
        {
          "title": "优刻得-W",
          "url": "https://xueqiu.com/s/SH688158",
          "source_name": "xueqiu"
        }
      ],
      "search_results": [
        {
          "title": "全民“养龙虾”点燃行情!优刻得20CM涨停,云计算板块雄起!华宝基金...",
          "url": "http://www.baidu.com/link?url=SAnoB3PhtjTKLgy5Cmy3iIfiElVgWC1l85YILMXNNPOYVykABqvT-och5vgSbL-hppvZOc3NFU8gf7T1zg2DTgkX7ez_kPs2mcR_d1zutNqoWTN7SamhgRYhrmKzbRtN",
          "source": "Search (baidu)"
        },
        {
          "title": "优刻得-W股票_数据_资料_信息 — 东方财富网",
          "url": "http://www.baidu.com/link?url=eal5Sox8snIAr7_t75UgDbQ360EOf5Evgzd6yz-aQR9RQdsWMMka4RJ5LxsKkjgvrHPMP96ER4_Qwv7GSf-w3_",
          "source": "Search (baidu)"
        },
        {
          "title": "放量突破20日均线,同样是牛股形态!(预警小公式) - 知乎",
          "url": "http://www.baidu.com/link?url=ZRwpJ_EjZQwaKK_ieF_4nij21WXjx1-V0skmpU-jLWsEBvr2MwE15mweP0BEIh81",
          "source": "Search (baidu)"
        },
        {
          "title": "大家还在搜突破10日均线是什么意思突破五日均线什么意思什么叫有效突破均线日均线ma60均线是啥意思放量突破20日均线成交量突破60日均量线如何看60日均线30周均线放量站上60日均线",
          "url": "/s?wd=%E7%AA%81%E7%A0%B410%E6%97%A5%E5%9D%87%E7%BA%BF%E6%98%AF%E4%BB%80%E4%B9%88%E6%84%8F%E6%80%9D&usm=1&ie=utf-8&rsv_pq=942d81b90016a3c3&oq=%E4%BC%98%E5%88%BB%E5%BE%97-W%E6%94%BE%E9%87%8F%E7%AA%81%E7%A0%B420%E6%97%A5%E5%9D%87%E7%BA%BF&rsv_t=3532CzQH1ELgFho1DElnY1wepwLPknwz%2FOrmH4qYKqr4pS63hiJwPhiqCCI&rsf=101633403&rsv_dl=0_prs_28608_1",
          "source": "Search (baidu)"
        },
        {
          "title": "优刻得-W(688158)_股票价格_行情_走势图—东方财富网",
          "url": "http://www.baidu.com/link?url=7y3ljFZMz2zT3M5gsvrdzbTn8S9CCyMhBamWo4B9Hg_esdLBU6PW7e63_gnyygdVe03rfhG8KgAjsSAqRSbJrK",
          "source": "Search (baidu)"
        }
      ]
    },
    {
      "signal_id": "inflation_stagflation_20260309",
      "title": "中东冲突持续 滞胀交易升温",
      "summary": "市场定价逻辑已从'软着陆'转向'滞胀'，能源板块受益于成本上升，高股息资产（长江电力）具备防御属性，而消费及成长板块承压。预计能源板块短期有5-10%的超额收益，高股息指数跑赢大盘。",
      "reasoning": "基于财联社报道，市场已迅速放弃中东冲突短期结束的预期，转而计入更长期的供应冲击。交易员押注美联储降息推迟至9月，这标志着全球交易逻辑由'通胀回落'切换至'滞胀交易'。在这种宏观环境下，能源板块直接受益于价格上行；高股息公用事业（如长江电力）因避险属性成为资金避风港；而白酒等顺周期消费股因受制于成本上升和经济下行压力，预期差在于市场仍部分高估了其防御属性。当前定价已部分反映能源利好，但尚未完全计入滞胀对高股息资产的防御溢价，存在博弈空间。",
      "transmission_chain": [
        {
          "node_name": "上游原材料/能源",
          "impact_type": "利好",
          "logic": "冲突导致能源供应中断预期升温，原油、天然气价格上行，直接提升石化及上游开采企业的营收与利润空间。"
        },
        {
          "node_name": "中游制造/周期品",
          "impact_type": "利空",
          "logic": "能源成本上升导致制造业运营成本增加，叠加对经济衰退的担忧，压制工业金属、化工品等周期股估值。"
        },
        {
          "node_name": "下游消费/白酒",
          "impact_type": "利空",
          "logic": "滞胀预期下，市场避险情绪升温，资金偏好从高估值消费股转向高股息资源股，消费股面临估值回调压力。"
        },
        {
          "node_name": "金融/利率",
          "impact_type": "中性偏利空",
          "logic": "市场预计美联储降息推迟至9月甚至不降息，长端利率维持高位，压制银行息差，但利好高股息资产。"
        }
      ],
      "sentiment_score": 0.0,
      "confidence": 0.7,
      "intensity": 4,
      "expectation_gap": 0.4,
      "timeliness": 0.6,
      "expected_horizon": "T+N",
      "price_in_status": "未知",
      "impact_tickers": [
        {
          "ticker": "600900",
          "name": "长江电力",
          "weight": 0.7,
          "impact_type": "中性偏多"
        }
      ],
      "industry_tags": [],
      "sources": [
        {
          "title": "“滞胀交易”席卷全球股市 市场放弃中东冲突迅速收场预期",
          "url": "https://www.cls.cn/detail/2307453",
          "source_name": "cls"
        }
      ],
      "search_results": [
        {
          "title": "中东局势升温,对A股影响几何?",
          "url": "http://www.baidu.com/link?url=tQirpP5aMJKmen_js3MMXljfu5H2o5bDK7p1arQdURr0BC7U5Lsj_DQXjfx8Q2u7uZzkjAoapr63NMZYU9_LPi-zkEI1xB0wyd9oXrZTkgy",
          "source": "Search (baidu)"
        },
        {
          "title": "滞胀交易席卷全球股市 交易员放弃中东冲突迅速收场预期",
          "url": "http://www.baidu.com/link?url=tQirpP5aMJKmen_js3MMXljfu5H2o5bDK7p1arQdURsWf1kqfbaJ-8tXQGcg8IFS-cwO1Z8Oe7S4PAYsDEtWbbOjZfvlHk_XTCmoZ7m04xu",
          "source": "Search (baidu)"
        },
        {
          "title": "中东局势突变!投资如何应对?基金经理最新研判",
          "url": "http://www.baidu.com/link?url=tQirpP5aMJKmen_js3MMXljfu5H2o5bDK7p1arQdURtPdpT_CYZYzgSVzwYdsFZxHxRnFgF57wOQKU_UQ09E1T-FV_SI8I9DagjTeokpfs3",
          "source": "Search (baidu)"
        },
        {
          "title": "大家还在搜中东地区为什么一直冲突不断中东怎么定义中东两大教派的冲突中东民族冲突中东冲突的根本原因中东关系中东战火再燃巴以缘何冲突再起中东局势是怎么回事",
          "url": "/s?wd=%E4%B8%AD%E4%B8%9C%E5%9C%B0%E5%8C%BA%E4%B8%BA%E4%BB%80%E4%B9%88%E4%B8%80%E7%9B%B4%E5%86%B2%E7%AA%81%E4%B8%8D%E6%96%AD&usm=1&ie=utf-8&rsv_pq=947286bd0014a985&oq=%E4%B8%AD%E4%B8%9C%E5%86%B2%E7%AA%81%E6%8C%81%E7%BB%AD%20%E6%BB%9E%E8%83%80%E4%BA%A4%E6%98%93%E5%8D%87%E6%B8%A9&rsv_t=1014QEyd2m7Ln%2BTBhrur9fuHYGzyJHZmTEj1lzCIMTrkeD0S52tCD3lAy7Y&rsf=101631202&rsv_dl=0_prs_28608_1",
          "source": "Search (baidu)"
        },
        {
          "title": "特朗普一句话震翻全球市场!油价狂飙17%,道指跌超600点,比特币失守6.8万...",
          "url": "http://www.baidu.com/link?url=J9C5dBz5-mqER1tnOXVnnZc3Ro5V1MV74C-w4wpQaccWfHYmHrD7LAXkwEhchqRaC7lKerDrd1rgK_JY7aDHKBW34ZoI_AybwXj8jVh8vgG",
          "source": "Search (baidu)"
        }
      ]
    },
    {
      "signal_id": "2307449",
      "title": "大商所上调苯乙烯等期货保证金",
      "summary": "大商所上调苯乙烯及上游纯苯期货保证金，反映监管层对相关品种波动加剧的担忧。虽然这是中性偏空的监管信号，但纯苯12%的涨跌停板调整幅度远超其他品种，预示上游原料价格波动风险显著加大。对于具备一体化优势的龙头（如万华、卫星），其成本端波动风险可控；而对于单纯依赖外采原料的下游，短期利润弹性可能被压缩。建议关注具备强成本转嫁能力的龙头，警惕纯苯价格剧烈波动带来的短期供应链冲击。",
      "reasoning": "该信号的核心在于监管层对市场风险的主动干预。数据显示，纯苯期货的涨跌停板调整幅度为7%→12%，远超苯乙烯本身的8%→11%，这释放了明确的信号：上游纯苯市场波动加剧。对于A股上市公司而言，化工品价格的剧烈波动通常通过两条路径传导：一是对冲成本增加（企业需投入更多资金进行套期保值），二是原材料成本波动加剧。万华化学和卫星化学作为一体化龙头企业，拥有自有化工装置，受外部纯苯价格剧烈波动的直接冲击相对较小，反而在市场动荡中具备更强的成本控制能力和市场份额优势。因此，虽然监管层此举意在降温，但纯苯价格的剧烈波动预期反而凸显了龙头企业的防御价值。当前股价尚未完全计入上游原材料剧烈波动的风险溢价，存在结构性机会。",
      "transmission_chain": [
        {
          "node_name": "大商所监管层",
          "impact_type": "中性",
          "logic": "大商所自3月10日起，将苯乙烯、乙二醇等主力合约涨跌停板由8%提升至11%，保证金由9%提升至13%，旨在应对市场波动，防范过度投机风险。"
        },
        {
          "node_name": "上游原材料端 (纯苯/乙烯)",
          "impact_type": "利空",
          "logic": "纯苯期货涨跌停板由7%大幅提升至12%，显示上游原料波动加剧。对于化工企业而言，原材料价格波动风险增加，短期成本控制压力增大，可能压缩利润空间。"
        },
        {
          "node_name": "中游化工品端 (苯乙烯/聚烯烃)",
          "impact_type": "中性偏空",
          "logic": "保证金提高意味着交易成本上升，短期投机资金可能流出，压制期货价格波动，进而对现货价格形成抑制。市场波动率预期上升，短期价格弹性增强。"
        },
        {
          "node_name": "下游应用端 (乳制品/包装)",
          "impact_type": "中性",
          "logic": "对于终端消费品企业（如乳企），上游化工原料（如聚丙烯包装材料）价格波动加大，虽长期可通过锁价对冲，但短期若原材料涨价过快，可能面临成本端压力。"
        }
      ],
      "sentiment_score": 0.0,
      "confidence": 0.5,
      "intensity": 3,
      "expectation_gap": 0.5,
      "timeliness": 0.8,
      "expected_horizon": "T+N",
      "price_in_status": "未知",
      "impact_tickers": [],
      "industry_tags": [],
      "sources": [
        {
          "title": "大商所调整苯乙烯等期货合约涨跌停板幅度和交易保证金水平",
          "url": "https://www.cls.cn/detail/2307449",
          "source_name": "cls"
        }
      ],
      "search_results": [
        {
          "title": "大商所调整苯乙烯等期货合约涨跌停板幅度和交易保证金水平",
          "url": "http://www.baidu.com/link?url=q6T0humuiTYps8a1Jxya4dQh6ZQbUbd5xPFz_tbxn6XVcc56yX3DFx9Clf-APbCgB-fAp2w7h5CK19kSopmctyu1lZ4RWH0LeQ_xV2ldJmG",
          "source": "Search (baidu)"
        },
        {
          "title": "关于调整苯乙烯等期货合约涨跌停板幅度和交易保证金水平的通知",
          "url": "http://www.baidu.com/link?url=oa4E7OgU7nMme2RNvp2fH5rOjJmPr7IOr0faI9-IVGREHlCWZOfoA1-blOWDZBqPcSpIux5BNwF1RKAks0aWi1kxmvd7UyAmCnmBgrC7pCa",
          "source": "Search (baidu)"
        },
        {
          "title": "大商所:调整苯乙烯等期货合约涨跌停板幅度和交易保证金水平",
          "url": "http://www.baidu.com/link?url=q6T0humuiTYps8a1Jxya4dQh6ZQbUbd5xPFz_tbxn6XVcc56yX3DFx9Clf-APbCgKj8-extq5o6fn-g4_Di6_IqAVS0MwcVG6qw4loAQdXy",
          "source": "Search (baidu)"
        },
        {
          "title": "大连商品交易所",
          "url": "http://www.baidu.com/link?url=V6EZU9OD4qkrSylZYtlW5qU0HnB0FdXq372MF-30Ofi",
          "source": "Search (baidu)"
        },
        {
          "title": "...大商所及郑商所部分期货相关合约交易保证金标准的通知|期货_新浪财经...",
          "url": "http://www.baidu.com/link?url=aCxeMEafkfOKvq5xMZ-b2k2xw9PyfIuK3VTYWHkszPix8vAIXfmhZheG1nx5We4op8HURzAYZECBmr0rSWbo3OXyxCjw3wZhgULvQT-8HXO",
          "source": "Search (baidu)"
        }
      ]
    }
  ],
  "charts": {
    "600938": {
      "ticker": "600938",
      "name": "中国海油",
      "prices": [
        {
          "date": "2026-02-09",
          "open": 34.2,
          "high": 34.41,
          "low": 33.93,
          "close": 34.09,
          "volume": 321419
        },
        {
          "date": "2026-02-10",
          "open": 34.29,
          "high": 34.86,
          "low": 34.26,
          "close": 34.32,
          "volume": 342298
        },
        {
          "date": "2026-02-11",
          "open": 34.28,
          "high": 34.98,
          "low": 33.91,
          "close": 34.83,
          "volume": 411834
        },
        {
          "date": "2026-02-12",
          "open": 35.02,
          "high": 35.68,
          "low": 34.95,
          "close": 35.54,
          "volume": 451580
        },
        {
          "date": "2026-02-13",
          "open": 34.5,
          "high": 34.75,
          "low": 34.06,
          "close": 34.39,
          "volume": 361054
        },
        {
          "date": "2026-02-24",
          "open": 35.8,
          "high": 37.26,
          "low": 35.78,
          "close": 37.22,
          "volume": 869021
        },
        {
          "date": "2026-02-25",
          "open": 37.3,
          "high": 37.3,
          "low": 35.85,
          "close": 36.39,
          "volume": 835455
        },
        {
          "date": "2026-02-26",
          "open": 36.11,
          "high": 36.46,
          "low": 35.4,
          "close": 35.47,
          "volume": 447882
        },
        {
          "date": "2026-02-27",
          "open": 35.48,
          "high": 35.93,
          "low": 35.29,
          "close": 35.87,
          "volume": 335828
        },
        {
          "date": "2026-03-02",
          "open": 39.46,
          "high": 39.46,
          "low": 37.9,
          "close": 39.46,
          "volume": 1772719
        },
        {
          "date": "2026-03-03",
          "open": 41.79,
          "high": 43.41,
          "low": 41.0,
          "close": 43.41,
          "volume": 2532802
        },
        {
          "date": "2026-03-04",
          "open": 44.5,
          "high": 44.5,
          "low": 39.07,
          "close": 42.85,
          "volume": 2625235
        },
        {
          "date": "2026-03-05",
          "open": 42.0,
          "high": 42.85,
          "low": 40.56,
          "close": 41.6,
          "volume": 1687169
        },
        {
          "date": "2026-03-06",
          "open": 40.67,
          "high": 42.38,
          "low": 39.66,
          "close": 40.49,
          "volume": 1227185
        },
        {
          "date": "2026-03-09",
          "open": 44.54,
          "high": 44.54,
          "low": 43.0,
          "close": 43.36,
          "volume": 2134154
        }
      ],
      "prediction_logic": "基于研究员提供的数据，中国海油当前股价43.36元，30日涨幅27.19%，处于强势上涨后的高位震荡阶段（最高44.54元）。尽管涨幅显著，但地缘政治导致的原油供给收缩逻辑尚未完全定价。短期关注44.54元阻力位，若突破可看至48-50元区间（+10%至+15%）；若遇阻回调，支撑位在41.60元附近（+4.5%）。建议关注3月10日开盘竞价及后续量能变化。"
    },
    "688158": {
      "ticker": "688158",
      "name": "优刻得-W",
      "prices": [
        {
          "date": "2026-02-09",
          "open": 35.7,
          "high": 35.84,
          "low": 34.44,
          "close": 35.42,
          "volume": 397140
        },
        {
          "date": "2026-02-10",
          "open": 35.42,
          "high": 36.56,
          "low": 35.18,
          "close": 35.71,
          "volume": 447964
        },
        {
          "date": "2026-02-11",
          "open": 35.49,
          "high": 39.0,
          "low": 35.49,
          "close": 37.54,
          "volume": 631041
        },
        {
          "date": "2026-02-12",
          "open": 43.2,
          "high": 45.05,
          "low": 40.47,
          "close": 45.05,
          "volume": 1043188
        },
        {
          "date": "2026-02-13",
          "open": 44.88,
          "high": 45.8,
          "low": 41.88,
          "close": 42.38,
          "volume": 973918
        },
        {
          "date": "2026-02-24",
          "open": 42.63,
          "high": 43.0,
          "low": 39.89,
          "close": 41.07,
          "volume": 560646
        },
        {
          "date": "2026-02-25",
          "open": 40.99,
          "high": 41.13,
          "low": 38.58,
          "close": 39.1,
          "volume": 516832
        },
        {
          "date": "2026-02-26",
          "open": 39.06,
          "high": 40.15,
          "low": 38.7,
          "close": 38.8,
          "volume": 575187
        },
        {
          "date": "2026-02-27",
          "open": 38.22,
          "high": 42.48,
          "low": 38.22,
          "close": 40.37,
          "volume": 753271
        },
        {
          "date": "2026-03-02",
          "open": 38.7,
          "high": 40.3,
          "low": 38.4,
          "close": 38.48,
          "volume": 495399
        },
        {
          "date": "2026-03-03",
          "open": 38.68,
          "high": 39.0,
          "low": 34.71,
          "close": 35.0,
          "volume": 525915
        },
        {
          "date": "2026-03-04",
          "open": 33.99,
          "high": 35.88,
          "low": 33.99,
          "close": 35.08,
          "volume": 301882
        },
        {
          "date": "2026-03-05",
          "open": 36.28,
          "high": 36.94,
          "low": 35.26,
          "close": 36.19,
          "volume": 383915
        },
        {
          "date": "2026-03-06",
          "open": 35.75,
          "high": 37.98,
          "low": 35.62,
          "close": 37.82,
          "volume": 415642
        },
        {
          "date": "2026-03-09",
          "open": 41.66,
          "high": 45.38,
          "low": 41.05,
          "close": 45.38,
          "volume": 706106
        }
      ],
      "prediction_logic": "优刻得-W (688158) 今日强势反攻，股价从低点33.99元累计反弹28.12%，现价45.38元逼近前期高点45.80元。短期目标位看向50.00元（突破阻力位），对应区间涨幅约10%-15%。建议关注20日均线(37.80)的支撑有效性及量能持续性。若回踩支撑位企稳，则上行空间打开。"
    },
    "600900": {
      "ticker": "600900",
      "name": "长江电力",
      "prices": [
        {
          "date": "2026-01-19",
          "open": 26.4,
          "high": 26.71,
          "low": 26.39,
          "close": 26.59,
          "volume": 1047218
        },
        {
          "date": "2026-01-20",
          "open": 26.59,
          "high": 26.73,
          "low": 26.52,
          "close": 26.67,
          "volume": 1050034
        },
        {
          "date": "2026-01-21",
          "open": 26.68,
          "high": 26.69,
          "low": 26.34,
          "close": 26.37,
          "volume": 1163282
        },
        {
          "date": "2026-01-22",
          "open": 26.37,
          "high": 26.51,
          "low": 26.09,
          "close": 26.1,
          "volume": 1807850
        },
        {
          "date": "2026-01-23",
          "open": 26.15,
          "high": 26.21,
          "low": 25.75,
          "close": 25.79,
          "volume": 2106915
        },
        {
          "date": "2026-01-26",
          "open": 25.84,
          "high": 26.07,
          "low": 25.65,
          "close": 25.77,
          "volume": 2028698
        },
        {
          "date": "2026-01-27",
          "open": 25.77,
          "high": 25.93,
          "low": 25.65,
          "close": 25.72,
          "volume": 1313815
        },
        {
          "date": "2026-01-28",
          "open": 25.72,
          "high": 25.73,
          "low": 25.4,
          "close": 25.44,
          "volume": 2326498
        },
        {
          "date": "2026-01-29",
          "open": 25.44,
          "high": 25.99,
          "low": 25.17,
          "close": 25.82,
          "volume": 2616230
        },
        {
          "date": "2026-01-30",
          "open": 25.83,
          "high": 26.36,
          "low": 25.83,
          "close": 26.15,
          "volume": 2238492
        },
        {
          "date": "2026-02-02",
          "open": 26.28,
          "high": 26.34,
          "low": 25.88,
          "close": 25.93,
          "volume": 1242257
        },
        {
          "date": "2026-02-03",
          "open": 25.99,
          "high": 26.02,
          "low": 25.7,
          "close": 25.79,
          "volume": 885438
        },
        {
          "date": "2026-02-04",
          "open": 25.76,
          "high": 26.18,
          "low": 25.74,
          "close": 26.17,
          "volume": 957052
        },
        {
          "date": "2026-02-05",
          "open": 26.21,
          "high": 26.48,
          "low": 26.14,
          "close": 26.39,
          "volume": 1032448
        },
        {
          "date": "2026-02-06",
          "open": 26.39,
          "high": 26.56,
          "low": 26.17,
          "close": 26.31,
          "volume": 725627
        },
        {
          "date": "2026-02-09",
          "open": 26.32,
          "high": 26.36,
          "low": 26.07,
          "close": 26.25,
          "volume": 678291
        },
        {
          "date": "2026-02-10",
          "open": 26.25,
          "high": 26.39,
          "low": 26.16,
          "close": 26.36,
          "volume": 559201
        },
        {
          "date": "2026-02-11",
          "open": 26.37,
          "high": 26.38,
          "low": 26.2,
          "close": 26.27,
          "volume": 533882
        },
        {
          "date": "2026-02-12",
          "open": 26.27,
          "high": 26.3,
          "low": 26.05,
          "close": 26.12,
          "volume": 737342
        },
        {
          "date": "2026-02-13",
          "open": 26.13,
          "high": 26.18,
          "low": 25.95,
          "close": 26.0,
          "volume": 715541
        },
        {
          "date": "2026-02-24",
          "open": 26.13,
          "high": 26.16,
          "low": 25.98,
          "close": 26.05,
          "volume": 730789
        },
        {
          "date": "2026-02-25",
          "open": 26.08,
          "high": 26.2,
          "low": 25.95,
          "close": 25.97,
          "volume": 956210
        },
        {
          "date": "2026-02-26",
          "open": 25.98,
          "high": 26.09,
          "low": 25.93,
          "close": 26.04,
          "volume": 619772
        },
        {
          "date": "2026-02-27",
          "open": 26.05,
          "high": 26.18,
          "low": 26.02,
          "close": 26.04,
          "volume": 919038
        },
        {
          "date": "2026-03-02",
          "open": 26.12,
          "high": 26.65,
          "low": 26.12,
          "close": 26.57,
          "volume": 1817729
        },
        {
          "date": "2026-03-03",
          "open": 26.57,
          "high": 27.1,
          "low": 26.53,
          "close": 26.97,
          "volume": 2145547
        },
        {
          "date": "2026-03-04",
          "open": 26.8,
          "high": 27.19,
          "low": 26.52,
          "close": 27.09,
          "volume": 1757354
        },
        {
          "date": "2026-03-05",
          "open": 26.98,
          "high": 27.24,
          "low": 26.84,
          "close": 27.08,
          "volume": 1329149
        },
        {
          "date": "2026-03-06",
          "open": 27.06,
          "high": 27.15,
          "low": 26.98,
          "close": 27.14,
          "volume": 878369
        },
        {
          "date": "2026-03-09",
          "open": 27.16,
          "high": 27.63,
          "low": 27.09,
          "close": 27.2,
          "volume": 2075028
        }
      ],
      "prediction": {
        "target_low": -1.8,
        "target_high": -0.7,
        "confidence": 65
      },
      "forecast": [
        {
          "date": "2026-03-10",
          "open": 26.97178840637207,
          "high": 27.16924285888672,
          "low": 26.778467178344727,
          "close": 27.007919311523438,
          "volume": 1259813.625
        },
        {
          "date": "2026-03-11",
          "open": 26.86212158203125,
          "high": 27.08599853515625,
          "low": 26.778005599975586,
          "close": 26.984567642211914,
          "volume": 979119.25
        },
        {
          "date": "2026-03-12",
          "open": 26.78089714050293,
          "high": 26.932828903198242,
          "low": 26.50199317932129,
          "close": 26.711978912353516,
          "volume": 1088845.75
        },
        {
          "date": "2026-03-13",
          "open": 26.595489501953125,
          "high": 26.807884216308594,
          "low": 26.506811141967773,
          "close": 26.71463394165039,
          "volume": 1022784.5
        },
        {
          "date": "2026-03-16",
          "open": 26.584280014038086,
          "high": 26.957538604736328,
          "low": 26.423057556152344,
          "close": 26.732946395874023,
          "volume": 1886797.75
        }
      ],
      "forecast_base": [
        {
          "date": "2026-03-10",
          "open": 27.05600357055664,
          "high": 27.362398147583008,
          "low": 27.025245666503906,
          "close": 27.300540924072266,
          "volume": 973586.875
        },
        {
          "date": "2026-03-11",
          "open": 27.167383193969727,
          "high": 27.342777252197266,
          "low": 26.963220596313477,
          "close": 27.103303909301758,
          "volume": 785394.75
        },
        {
          "date": "2026-03-12",
          "open": 26.92827033996582,
          "high": 27.2293701171875,
          "low": 26.76898193359375,
          "close": 26.906070709228516,
          "volume": 1259607.5
        },
        {
          "date": "2026-03-13",
          "open": 26.814672470092773,
          "high": 26.992774963378906,
          "low": 26.528976440429688,
          "close": 26.691320419311523,
          "volume": 1006245.0625
        },
        {
          "date": "2026-03-16",
          "open": 26.60792350769043,
          "high": 27.043916702270508,
          "low": 26.49527359008789,
          "close": 26.522192001342773,
          "volume": 1130712.0
        }
      ],
      "prediction_logic": "市场定价逻辑已从'软着陆'转向'滞胀'，能源板块受益于成本上升，高股息资产（长江电力）具备防御属性，而消费及成长板块承压。预计能源板块短期有5-10%的超额收益，高股息指数跑赢大盘。"
    }
  }
}