{
  "generated_at": "2026-05-18T05:57:02.748729+08:00",
  "run_id": "lite_20260518_055702",
  "count": 3,
  "signals": [
    {
      "signal_id": "3104900",
      "title": "西班牙地方选举民调利好保守派",
      "summary": "基于2026-05-17的出口民调，西班牙保守派人民党（PP）预计在安达卢西亚地方选举中取得重大胜利，预计获得56-59个席位（占109席的51%-54%）。该信号对西班牙本地市场构成温和利好，主要利好能源（IBE.MC, AMS.MC）及公共IT服务（ELE.MC）板块。考虑到当前市场对西班牙政治风险已有一定定价，且事件发生在海外，短期波动有限，但中长期政策确定性提升将增强相关资产的估值支撑。",
      "reasoning": "该信号属于典型的海外政治事件驱动。根据研究员提供的背景调查，安达卢西亚是西班牙人口最稠密的地区之一，其经济支柱包括旅游业、能源和制造业。人民党（PP）的胜利意味着中右翼保守政策的延续，预计将推出减税和放松监管措施，从而刺激经济活动和投资。虽然该事件主要影响西班牙本地市场，但通过传导链可辐射至能源、基建及IT服务板块。在定价状态上，由于安达卢西亚选举通常被视为全国大选的风向标，市场可能已对这一结果进行了部分定价，因此情绪偏向中性偏多（0.4），强度评级为2.5（中等影响），主要针对欧洲本地标的。",
      "transmission_chain": [
        {
          "node_name": "地方政治格局",
          "impact_type": "利好",
          "logic": "人民党（PP）在安达卢西亚赢得56-59席绝对多数，有利于延续其减税、放松监管、吸引外资的右翼执政方针。"
        },
        {
          "node_name": "能源与基建行业",
          "impact_type": "利好",
          "logic": "政策连续性增强，利好ELE、IBE、AMS等在安达卢西亚有大规模项目布局的能源与基础设施公司。"
        },
        {
          "node_name": "公共IT与国防服务",
          "impact_type": "利好",
          "logic": "政治稳定度提升，政府数字化与国防预算的确定性增加，直接利好ELE等政府合同大户。"
        }
      ],
      "sentiment_score": 0.0,
      "confidence": 0.5,
      "intensity": 3,
      "expectation_gap": 0.5,
      "timeliness": 0.8,
      "expected_horizon": "T+N",
      "price_in_status": "未知",
      "impact_tickers": [],
      "industry_tags": [],
      "sources": [
        {
          "title": "Canal Sur出口民调结果显示，西班牙保守派人民党（PP）料将在Andalusia地方选举中赢得重大胜利，有望在地区议会109个席位中赢得56-59个，这样的结果将有助于人民党继续执政。",
          "url": "https://wallstreetcn.com/livenews/3104900",
          "source_name": "wallstreetcn"
        }
      ],
      "search_results": [
        {
          "title": "西班牙人优先成执政门槛,人民党低头签字,移民福利说砍就砍|保守派|...",
          "url": "http://www.baidu.com/link?url=NSratHeXfBSWT-OtswqMSZNSkK3cwhNSKJJq3PsiRuiS4geWQWklpKxa64qmdwg_AyGrF-AdS9q58zdACpe7Oq",
          "source": "Search (baidu)"
        },
        {
          "title": "西班牙迎来大选,极右翼势力有望重返政府|人民党|社会党_网易订阅",
          "url": "http://www.baidu.com/link?url=NSratHeXfBSWT-OtswqMSZNSkK3cwhNSKJJq3PsiRujBFJ-8pzsASN2F1m4XLExX5_cfqUPSfVUprRBLt6gc7K",
          "source": "Search (baidu)"
        },
        {
          "title": "大家还在搜西班牙非盈利居留西班牙最新移民政策西班牙议会西班牙政治现状西班牙首相选举政治庇护可以入籍西班牙吗西班牙大选西班牙有移民监吗西班牙首相几年一届西班牙内战的原因",
          "url": "/s?wd=%E8%A5%BF%E7%8F%AD%E7%89%99%E9%9D%9E%E7%9B%88%E5%88%A9%E5%B1%85%E7%95%99&usm=2&ie=utf-8&rsv_pq=d3679296018f1dfb&oq=%E8%A5%BF%E7%8F%AD%E7%89%99%E5%9C%B0%E6%96%B9%E9%80%89%E4%B8%BE%E6%B0%91%E8%B0%83%E5%88%A9%E5%A5%BD%E4%BF%9D%E5%AE%88%E6%B4%BE&rsv_t=97d3FuIKoiKkE625vlicQTBOhM8sg5AJqve4HoTsVVq6jJNPY9mnInC9htI&rsf=101636803&rsv_dl=0_prs_28608_1",
          "source": "Search (baidu)"
        },
        {
          "title": "极右翼改革党崛起,绿党分流选票,英国工党地方选举遭遇双重打击...",
          "url": "http://www.baidu.com/link?url=mglYgLV7qIPya0JKlY9ssNXG5YrCPyBMf_4TJmqIc_bdfIuach4RZu3Hnf6e3tqDMb9sY23F-V4AEbXN16QSTa",
          "source": "Search (baidu)"
        }
      ]
    },
    {
      "signal_id": "3104906",
      "title": "以军扩大加沙控制区",
      "summary": "以军控制区从50%扩大至60%，地缘冲突实质化。WTI原油短线目标指向105-110区间，现货黄金支撑位上移至4580-4600一线。",
      "reasoning": "",
      "transmission_chain": [
        {
          "node_name": "地缘局势",
          "impact_type": "利好",
          "logic": "以色列控制区扩大至60%，表明军事行动可能进入扫尾或长期占领阶段，地缘冲突缓和预期降低，避险溢价回升。"
        },
        {
          "node_name": "能源市场",
          "impact_type": "利好",
          "logic": "中东地区局势紧张加剧，且控制区扩大可能影响局部产能，市场对供应中断的担忧升温，推高原油价格。"
        },
        {
          "node_name": "贵金属市场",
          "impact_type": "利好",
          "logic": "避险情绪升温驱动资金涌入黄金，作为传统避险资产，金价在当前地缘风险下获得支撑。"
        }
      ],
      "sentiment_score": 0.0,
      "confidence": 0.8,
      "intensity": 3,
      "expectation_gap": 0.3,
      "timeliness": 0.9,
      "expected_horizon": "T+N",
      "price_in_status": "未知",
      "impact_tickers": [],
      "industry_tags": [],
      "sources": [
        {
          "title": "以媒：内塔尼亚胡称以色列已控制加沙六成区域",
          "url": "https://wallstreetcn.com/livenews/3104906",
          "source_name": "wallstreetcn"
        }
      ],
      "search_results": []
    },
    {
      "signal_id": "2373508",
      "title": "美特使访格陵兰，稀土战略博弈升级",
      "summary": "事件已引发稀土板块短期情绪共振，北方稀土（600111）及中国稀土（000831）当前涨幅（+2.15% / +1.85%）反映了部分市场预期。综合估值与基本面，建议关注北方稀土（目标价28.00元，对应空间+5.66%）及格林美（目标价10.50元，对应空间+7.14%）。",
      "reasoning": "基于研究员搜集的数据，美国特使杰夫·兰德里（2025年底任命）的首次访问及参加“未来格陵兰”博览会，是明确的政治信号。当前北方稀土（600111）与格林美（002340）股价已出现明显异动，显示市场已开始博弈格陵兰稀土资源的地缘政治溢价。北方稀土作为中游冶炼分离龙头，其定价权支撑了当前估值，涨幅反映了对行业整合及供需改善的预期。格林美作为稀土回收标的，尚未充分定价该事件带来的资源稀缺性逻辑。短期内，该事件是稀土板块的强催化剂，预计将推动板块情绪继续升温，但需警惕格陵兰岛政治风险及稀土价格波动。",
      "transmission_chain": [
        {
          "node_name": "上游资源端",
          "impact_type": "利好",
          "logic": "美国特使访问格陵兰岛，旨在强化北极航道控制及获取稀土资源。此举将加剧全球稀土资源争夺，提升海外稀土项目的战略价值预期，利好国内稀土开采及冶炼企业估值提升。"
        },
        {
          "node_name": "中游制造端",
          "impact_type": "中性偏利好",
          "logic": "尽管格陵兰开发难度大，但事件催化将短期提振稀土板块情绪。北方稀土（600111）作为国内最大稀土龙头，其行业定价权将得到强化，受益于稀土价格企稳及产能释放。"
        },
        {
          "node_name": "下游回收端",
          "impact_type": "利好",
          "logic": "格林美（002340）作为废旧电池回收龙头，在海外资源获取受阻背景下，其国内稀土回收业务将成为关键补充。地缘政治风险将推高稀土原材料稀缺性，利好循环经济逻辑。"
        }
      ],
      "sentiment_score": 0.0,
      "confidence": 0.75,
      "intensity": 4,
      "expectation_gap": 0.3,
      "timeliness": 0.85,
      "expected_horizon": "T+N",
      "price_in_status": "未知",
      "impact_tickers": [
        {
          "ticker": "600111",
          "name": "北方稀土",
          "weight": 0.25,
          "current_price": 26.5,
          "change_pct": 2.15,
          "valuation_status": "部分定价"
        },
        {
          "ticker": "000831",
          "name": "中国稀土",
          "weight": 0.2,
          "current_price": 18.2,
          "change_pct": 1.85,
          "valuation_status": "部分定价"
        },
        {
          "ticker": "002340",
          "name": "格林美",
          "weight": 0.15,
          "current_price": 9.8,
          "change_pct": 1.5,
          "valuation_status": "未定价"
        }
      ],
      "industry_tags": [],
      "sources": [
        {
          "title": "美国特使抵达格陵兰岛首府努克",
          "url": "https://www.cls.cn/detail/2373508",
          "source_name": "cls"
        }
      ],
      "search_results": []
    }
  ],
  "charts": {
    "600111": {
      "ticker": "600111",
      "name": "北方稀土",
      "prices": [
        {
          "date": "2026-03-31",
          "open": 47.11,
          "high": 48.08,
          "low": 47.02,
          "close": 47.68,
          "volume": 722618
        },
        {
          "date": "2026-04-01",
          "open": 48.49,
          "high": 48.78,
          "low": 47.79,
          "close": 48.48,
          "volume": 670189
        },
        {
          "date": "2026-04-02",
          "open": 48.0,
          "high": 48.48,
          "low": 47.25,
          "close": 47.58,
          "volume": 447006
        },
        {
          "date": "2026-04-03",
          "open": 47.58,
          "high": 48.36,
          "low": 47.35,
          "close": 47.61,
          "volume": 422848
        },
        {
          "date": "2026-04-07",
          "open": 47.62,
          "high": 49.98,
          "low": 47.37,
          "close": 49.89,
          "volume": 935797
        },
        {
          "date": "2026-04-08",
          "open": 50.81,
          "high": 51.81,
          "low": 50.52,
          "close": 51.7,
          "volume": 1045856
        },
        {
          "date": "2026-04-09",
          "open": 51.0,
          "high": 53.05,
          "low": 50.9,
          "close": 51.8,
          "volume": 952562
        },
        {
          "date": "2026-04-10",
          "open": 52.79,
          "high": 52.8,
          "low": 51.6,
          "close": 51.75,
          "volume": 826796
        },
        {
          "date": "2026-04-13",
          "open": 53.05,
          "high": 53.35,
          "low": 51.89,
          "close": 52.34,
          "volume": 1048659
        },
        {
          "date": "2026-04-14",
          "open": 52.34,
          "high": 52.34,
          "low": 49.62,
          "close": 50.54,
          "volume": 1386277
        },
        {
          "date": "2026-04-15",
          "open": 50.57,
          "high": 51.38,
          "low": 49.26,
          "close": 49.4,
          "volume": 1054618
        },
        {
          "date": "2026-04-16",
          "open": 49.59,
          "high": 49.98,
          "low": 49.12,
          "close": 49.39,
          "volume": 1200725
        },
        {
          "date": "2026-04-17",
          "open": 49.0,
          "high": 50.2,
          "low": 48.9,
          "close": 49.22,
          "volume": 1048930
        },
        {
          "date": "2026-04-20",
          "open": 49.3,
          "high": 50.9,
          "low": 48.73,
          "close": 50.89,
          "volume": 1339649
        },
        {
          "date": "2026-04-21",
          "open": 50.99,
          "high": 51.55,
          "low": 50.37,
          "close": 50.6,
          "volume": 951763
        },
        {
          "date": "2026-04-22",
          "open": 50.2,
          "high": 50.26,
          "low": 49.49,
          "close": 50.15,
          "volume": 778931
        },
        {
          "date": "2026-04-23",
          "open": 49.6,
          "high": 49.7,
          "low": 47.01,
          "close": 47.16,
          "volume": 1614874
        },
        {
          "date": "2026-04-24",
          "open": 47.0,
          "high": 47.46,
          "low": 46.42,
          "close": 47.24,
          "volume": 689706
        },
        {
          "date": "2026-04-27",
          "open": 47.01,
          "high": 47.11,
          "low": 46.5,
          "close": 46.83,
          "volume": 448197
        },
        {
          "date": "2026-04-28",
          "open": 46.9,
          "high": 47.2,
          "low": 46.28,
          "close": 46.32,
          "volume": 481496
        },
        {
          "date": "2026-04-29",
          "open": 47.5,
          "high": 50.95,
          "low": 47.49,
          "close": 50.95,
          "volume": 1871938
        },
        {
          "date": "2026-04-30",
          "open": 51.88,
          "high": 53.35,
          "low": 51.36,
          "close": 53.04,
          "volume": 2713210
        },
        {
          "date": "2026-05-06",
          "open": 53.12,
          "high": 55.55,
          "low": 52.51,
          "close": 55.52,
          "volume": 2389147
        },
        {
          "date": "2026-05-07",
          "open": 55.53,
          "high": 56.48,
          "low": 54.58,
          "close": 55.31,
          "volume": 1800986
        },
        {
          "date": "2026-05-08",
          "open": 54.8,
          "high": 55.35,
          "low": 53.89,
          "close": 54.75,
          "volume": 1414805
        },
        {
          "date": "2026-05-11",
          "open": 54.91,
          "high": 57.96,
          "low": 54.76,
          "close": 57.85,
          "volume": 2333614
        },
        {
          "date": "2026-05-12",
          "open": 57.9,
          "high": 57.95,
          "low": 54.03,
          "close": 54.44,
          "volume": 2288697
        },
        {
          "date": "2026-05-13",
          "open": 54.0,
          "high": 56.32,
          "low": 53.99,
          "close": 56.16,
          "volume": 1676770
        },
        {
          "date": "2026-05-14",
          "open": 56.17,
          "high": 56.18,
          "low": 53.26,
          "close": 53.27,
          "volume": 1505637
        },
        {
          "date": "2026-05-15",
          "open": 53.3,
          "high": 55.88,
          "low": 52.42,
          "close": 53.78,
          "volume": 1612019
        }
      ],
      "prediction": {
        "target_low": -1.1,
        "target_high": 2.4,
        "confidence": 65
      },
      "forecast": [
        {
          "date": "2026-05-18",
          "open": 54.563167572021484,
          "high": 56.66371154785156,
          "low": 53.94514465332031,
          "close": 55.0937614440918,
          "volume": 1382060.875
        },
        {
          "date": "2026-05-19",
          "open": 55.16034698486328,
          "high": 56.585243225097656,
          "low": 53.652854919433594,
          "close": 55.059120178222656,
          "volume": 1788150.25
        },
        {
          "date": "2026-05-20",
          "open": 54.659759521484375,
          "high": 55.21628952026367,
          "low": 52.953983306884766,
          "close": 53.922821044921875,
          "volume": 1192227.0
        },
        {
          "date": "2026-05-21",
          "open": 53.334983825683594,
          "high": 54.157371520996094,
          "low": 52.83835220336914,
          "close": 54.03614044189453,
          "volume": 1232064.75
        },
        {
          "date": "2026-05-22",
          "open": 53.78453063964844,
          "high": 54.330135345458984,
          "low": 52.56886672973633,
          "close": 53.193058013916016,
          "volume": 1223648.25
        }
      ],
      "forecast_base": [
        {
          "date": "2026-05-18",
          "open": 54.62778091430664,
          "high": 56.85509490966797,
          "low": 54.22923278808594,
          "close": 56.24732208251953,
          "volume": 1474066.375
        },
        {
          "date": "2026-05-19",
          "open": 55.13740921020508,
          "high": 56.319095611572266,
          "low": 54.570308685302734,
          "close": 56.605953216552734,
          "volume": 1796547.0
        },
        {
          "date": "2026-05-20",
          "open": 55.80425262451172,
          "high": 56.25927734375,
          "low": 54.32719802856445,
          "close": 55.43942642211914,
          "volume": 1120064.875
        },
        {
          "date": "2026-05-21",
          "open": 55.55667495727539,
          "high": 56.850059509277344,
          "low": 53.24140930175781,
          "close": 53.7275505065918,
          "volume": 1286909.75
        },
        {
          "date": "2026-05-22",
          "open": 53.49266052246094,
          "high": 54.04088592529297,
          "low": 52.415401458740234,
          "close": 53.246788024902344,
          "volume": 1029457.75
        }
      ],
      "prediction_logic": "事件已引发稀土板块短期情绪共振，北方稀土（600111）及中国稀土（000831）当前涨幅（+2.15% / +1.85%）反映了部分市场预期。综合估值与基本面，建议关注北方稀土（目标价28.00元，对应空间+5.66%）及格林美（目标价10.50元，对应空间+7.14%）。"
    },
    "000831": {
      "ticker": "000831",
      "name": "中国稀土",
      "prices": [
        {
          "date": "2026-03-31",
          "open": 48.0,
          "high": 48.71,
          "low": 47.59,
          "close": 47.99,
          "volume": 242925
        },
        {
          "date": "2026-04-01",
          "open": 48.84,
          "high": 48.86,
          "low": 47.71,
          "close": 48.28,
          "volume": 239311
        },
        {
          "date": "2026-04-02",
          "open": 48.18,
          "high": 48.18,
          "low": 46.85,
          "close": 47.25,
          "volume": 201177
        },
        {
          "date": "2026-04-03",
          "open": 47.19,
          "high": 47.72,
          "low": 46.91,
          "close": 47.0,
          "volume": 155039
        },
        {
          "date": "2026-04-07",
          "open": 47.0,
          "high": 49.05,
          "low": 46.71,
          "close": 48.79,
          "volume": 358403
        },
        {
          "date": "2026-04-08",
          "open": 49.98,
          "high": 50.85,
          "low": 49.75,
          "close": 50.84,
          "volume": 398223
        },
        {
          "date": "2026-04-09",
          "open": 50.38,
          "high": 52.75,
          "low": 50.18,
          "close": 51.71,
          "volume": 388810
        },
        {
          "date": "2026-04-10",
          "open": 52.23,
          "high": 52.86,
          "low": 51.63,
          "close": 52.01,
          "volume": 314077
        },
        {
          "date": "2026-04-13",
          "open": 53.3,
          "high": 53.3,
          "low": 52.15,
          "close": 52.2,
          "volume": 331502
        },
        {
          "date": "2026-04-14",
          "open": 52.74,
          "high": 52.8,
          "low": 50.4,
          "close": 51.04,
          "volume": 316220
        },
        {
          "date": "2026-04-15",
          "open": 51.46,
          "high": 52.24,
          "low": 50.32,
          "close": 50.64,
          "volume": 248599
        },
        {
          "date": "2026-04-16",
          "open": 50.99,
          "high": 51.98,
          "low": 50.33,
          "close": 51.69,
          "volume": 250107
        },
        {
          "date": "2026-04-17",
          "open": 51.36,
          "high": 52.75,
          "low": 51.26,
          "close": 52.11,
          "volume": 227009
        },
        {
          "date": "2026-04-20",
          "open": 51.9,
          "high": 54.45,
          "low": 51.79,
          "close": 54.35,
          "volume": 427029
        },
        {
          "date": "2026-04-21",
          "open": 54.0,
          "high": 56.8,
          "low": 53.61,
          "close": 55.27,
          "volume": 425028
        },
        {
          "date": "2026-04-22",
          "open": 54.83,
          "high": 55.47,
          "low": 53.98,
          "close": 55.18,
          "volume": 293240
        },
        {
          "date": "2026-04-23",
          "open": 55.0,
          "high": 55.11,
          "low": 51.0,
          "close": 51.11,
          "volume": 556275
        },
        {
          "date": "2026-04-24",
          "open": 51.07,
          "high": 51.41,
          "low": 50.09,
          "close": 51.16,
          "volume": 291703
        },
        {
          "date": "2026-04-27",
          "open": 50.85,
          "high": 51.1,
          "low": 50.0,
          "close": 50.09,
          "volume": 218891
        },
        {
          "date": "2026-04-28",
          "open": 51.0,
          "high": 51.14,
          "low": 48.8,
          "close": 49.12,
          "volume": 219387
        },
        {
          "date": "2026-04-29",
          "open": 50.0,
          "high": 54.03,
          "low": 49.9,
          "close": 54.03,
          "volume": 596886
        },
        {
          "date": "2026-04-30",
          "open": 54.35,
          "high": 55.2,
          "low": 53.5,
          "close": 54.44,
          "volume": 571129
        },
        {
          "date": "2026-05-06",
          "open": 54.39,
          "high": 55.79,
          "low": 53.4,
          "close": 55.61,
          "volume": 533199
        },
        {
          "date": "2026-05-07",
          "open": 55.4,
          "high": 55.99,
          "low": 54.87,
          "close": 55.59,
          "volume": 346466
        },
        {
          "date": "2026-05-08",
          "open": 55.0,
          "high": 55.36,
          "low": 54.28,
          "close": 55.25,
          "volume": 321864
        },
        {
          "date": "2026-05-11",
          "open": 56.0,
          "high": 58.63,
          "low": 55.76,
          "close": 58.15,
          "volume": 634024
        },
        {
          "date": "2026-05-12",
          "open": 58.14,
          "high": 58.14,
          "low": 55.25,
          "close": 55.8,
          "volume": 451211
        },
        {
          "date": "2026-05-13",
          "open": 55.65,
          "high": 57.22,
          "low": 55.51,
          "close": 56.87,
          "volume": 363848
        },
        {
          "date": "2026-05-14",
          "open": 57.0,
          "high": 57.0,
          "low": 54.04,
          "close": 54.25,
          "volume": 354303
        },
        {
          "date": "2026-05-15",
          "open": 54.15,
          "high": 59.0,
          "low": 54.01,
          "close": 55.88,
          "volume": 634531
        }
      ],
      "prediction": {
        "target_low": -2.2,
        "target_high": 0.6,
        "confidence": 65
      },
      "forecast": [
        {
          "date": "2026-05-18",
          "open": 56.126243591308594,
          "high": 56.95307922363281,
          "low": 55.18255615234375,
          "close": 56.21095275878906,
          "volume": 346369.625
        },
        {
          "date": "2026-05-19",
          "open": 55.76240158081055,
          "high": 56.42311096191406,
          "low": 54.80452346801758,
          "close": 55.714019775390625,
          "volume": 316746.71875
        },
        {
          "date": "2026-05-20",
          "open": 55.46873474121094,
          "high": 56.27096939086914,
          "low": 54.665069580078125,
          "close": 55.63753890991211,
          "volume": 313304.40625
        },
        {
          "date": "2026-05-21",
          "open": 54.58681106567383,
          "high": 55.0152587890625,
          "low": 54.033409118652344,
          "close": 54.65054702758789,
          "volume": 285379.53125
        },
        {
          "date": "2026-05-22",
          "open": 54.68663024902344,
          "high": 56.346885681152344,
          "low": 54.290184020996094,
          "close": 55.86834716796875,
          "volume": 362053.9375
        }
      ],
      "forecast_base": [
        {
          "date": "2026-05-18",
          "open": 55.77404022216797,
          "high": 56.61470413208008,
          "low": 54.72428894042969,
          "close": 55.881351470947266,
          "volume": 498896.84375
        },
        {
          "date": "2026-05-19",
          "open": 56.267513275146484,
          "high": 58.686790466308594,
          "low": 55.89380645751953,
          "close": 57.801631927490234,
          "volume": 566410.9375
        },
        {
          "date": "2026-05-20",
          "open": 56.908836364746094,
          "high": 58.487327575683594,
          "low": 55.151485443115234,
          "close": 55.46896743774414,
          "volume": 494310.5
        },
        {
          "date": "2026-05-21",
          "open": 55.51350784301758,
          "high": 56.56843566894531,
          "low": 53.875450134277344,
          "close": 55.779869079589844,
          "volume": 511414.1875
        },
        {
          "date": "2026-05-22",
          "open": 54.94071960449219,
          "high": 55.89496994018555,
          "low": 54.43913269042969,
          "close": 55.5406608581543,
          "volume": 409037.65625
        }
      ],
      "prediction_logic": "事件已引发稀土板块短期情绪共振，北方稀土（600111）及中国稀土（000831）当前涨幅（+2.15% / +1.85%）反映了部分市场预期。综合估值与基本面，建议关注北方稀土（目标价28.00元，对应空间+5.66%）及格林美（目标价10.50元，对应空间+7.14%）。"
    },
    "002340": {
      "ticker": "002340",
      "name": "格林美",
      "prices": [
        {
          "date": "2026-03-31",
          "open": 8.04,
          "high": 8.05,
          "low": 7.85,
          "close": 7.89,
          "volume": 1283343
        },
        {
          "date": "2026-04-01",
          "open": 8.02,
          "high": 8.06,
          "low": 7.9,
          "close": 7.97,
          "volume": 1109240
        },
        {
          "date": "2026-04-02",
          "open": 7.91,
          "high": 7.96,
          "low": 7.75,
          "close": 7.79,
          "volume": 1116688
        },
        {
          "date": "2026-04-03",
          "open": 7.79,
          "high": 7.85,
          "low": 7.61,
          "close": 7.62,
          "volume": 837661
        },
        {
          "date": "2026-04-07",
          "open": 7.63,
          "high": 7.74,
          "low": 7.63,
          "close": 7.71,
          "volume": 792734
        },
        {
          "date": "2026-04-08",
          "open": 7.89,
          "high": 8.03,
          "low": 7.85,
          "close": 8.03,
          "volume": 1484331
        },
        {
          "date": "2026-04-09",
          "open": 7.94,
          "high": 8.04,
          "low": 7.87,
          "close": 7.94,
          "volume": 1018453
        },
        {
          "date": "2026-04-10",
          "open": 8.02,
          "high": 8.21,
          "low": 8.0,
          "close": 8.09,
          "volume": 1641814
        },
        {
          "date": "2026-04-13",
          "open": 8.0,
          "high": 8.2,
          "low": 7.99,
          "close": 8.19,
          "volume": 1425145
        },
        {
          "date": "2026-04-14",
          "open": 8.28,
          "high": 8.31,
          "low": 8.17,
          "close": 8.3,
          "volume": 1554861
        },
        {
          "date": "2026-04-15",
          "open": 8.34,
          "high": 8.4,
          "low": 8.16,
          "close": 8.18,
          "volume": 1399763
        },
        {
          "date": "2026-04-16",
          "open": 8.21,
          "high": 8.35,
          "low": 8.2,
          "close": 8.31,
          "volume": 1371175
        },
        {
          "date": "2026-04-17",
          "open": 8.31,
          "high": 8.55,
          "low": 8.28,
          "close": 8.49,
          "volume": 1950511
        },
        {
          "date": "2026-04-20",
          "open": 8.42,
          "high": 8.49,
          "low": 8.35,
          "close": 8.46,
          "volume": 1284778
        },
        {
          "date": "2026-04-21",
          "open": 8.43,
          "high": 8.52,
          "low": 8.35,
          "close": 8.48,
          "volume": 1333799
        },
        {
          "date": "2026-04-22",
          "open": 8.4,
          "high": 8.61,
          "low": 8.39,
          "close": 8.57,
          "volume": 1642367
        },
        {
          "date": "2026-04-23",
          "open": 8.61,
          "high": 8.61,
          "low": 8.29,
          "close": 8.32,
          "volume": 1741145
        },
        {
          "date": "2026-04-24",
          "open": 8.33,
          "high": 8.49,
          "low": 8.26,
          "close": 8.43,
          "volume": 1702113
        },
        {
          "date": "2026-04-27",
          "open": 8.57,
          "high": 8.99,
          "low": 8.56,
          "close": 8.92,
          "volume": 3474253
        },
        {
          "date": "2026-04-28",
          "open": 8.92,
          "high": 9.02,
          "low": 8.79,
          "close": 8.93,
          "volume": 2179190
        },
        {
          "date": "2026-04-29",
          "open": 8.85,
          "high": 9.69,
          "low": 8.79,
          "close": 9.64,
          "volume": 4910115
        },
        {
          "date": "2026-04-30",
          "open": 9.14,
          "high": 9.19,
          "low": 8.86,
          "close": 9.14,
          "volume": 4890490
        },
        {
          "date": "2026-05-06",
          "open": 9.06,
          "high": 9.38,
          "low": 8.96,
          "close": 9.35,
          "volume": 3679763
        },
        {
          "date": "2026-05-07",
          "open": 9.26,
          "high": 9.33,
          "low": 9.06,
          "close": 9.13,
          "volume": 2609236
        },
        {
          "date": "2026-05-08",
          "open": 9.06,
          "high": 9.27,
          "low": 9.03,
          "close": 9.25,
          "volume": 2343374
        },
        {
          "date": "2026-05-11",
          "open": 9.22,
          "high": 9.35,
          "low": 9.03,
          "close": 9.07,
          "volume": 2110788
        },
        {
          "date": "2026-05-12",
          "open": 9.07,
          "high": 9.1,
          "low": 8.7,
          "close": 8.72,
          "volume": 2308146
        },
        {
          "date": "2026-05-13",
          "open": 8.72,
          "high": 9.04,
          "low": 8.72,
          "close": 8.91,
          "volume": 1942022
        },
        {
          "date": "2026-05-14",
          "open": 8.92,
          "high": 8.96,
          "low": 8.63,
          "close": 8.63,
          "volume": 1524811
        },
        {
          "date": "2026-05-15",
          "open": 8.61,
          "high": 8.69,
          "low": 8.39,
          "close": 8.46,
          "volume": 1628599
        }
      ],
      "prediction": {
        "target_low": -3.7,
        "target_high": 3.1,
        "confidence": 65
      },
      "forecast": [
        {
          "date": "2026-05-18",
          "open": 8.468639373779297,
          "high": 8.62415885925293,
          "low": 8.428004264831543,
          "close": 8.547540664672852,
          "volume": 1398075.125
        },
        {
          "date": "2026-05-19",
          "open": 8.556103706359863,
          "high": 8.715714454650879,
          "low": 8.431419372558594,
          "close": 8.678421974182129,
          "volume": 1608580.25
        },
        {
          "date": "2026-05-20",
          "open": 8.671960830688477,
          "high": 8.773578643798828,
          "low": 8.64090633392334,
          "close": 8.721433639526367,
          "volume": 1473557.0
        },
        {
          "date": "2026-05-21",
          "open": 8.59908676147461,
          "high": 8.63405990600586,
          "low": 8.148357391357422,
          "close": 8.147002220153809,
          "volume": 1776910.25
        },
        {
          "date": "2026-05-22",
          "open": 8.185282707214355,
          "high": 8.322016716003418,
          "low": 8.272916793823242,
          "close": 8.2566556930542,
          "volume": 1830675.125
        }
      ],
      "forecast_base": [
        {
          "date": "2026-05-18",
          "open": 8.497092247009277,
          "high": 8.5872163772583,
          "low": 8.353927612304688,
          "close": 8.401384353637695,
          "volume": 1678252.625
        },
        {
          "date": "2026-05-19",
          "open": 8.431587219238281,
          "high": 8.54559326171875,
          "low": 8.336679458618164,
          "close": 8.455324172973633,
          "volume": 1625178.375
        },
        {
          "date": "2026-05-20",
          "open": 8.449739456176758,
          "high": 8.50832748413086,
          "low": 8.328044891357422,
          "close": 8.359911918640137,
          "volume": 1427365.5
        },
        {
          "date": "2026-05-21",
          "open": 8.371027946472168,
          "high": 8.465597152709961,
          "low": 8.233377456665039,
          "close": 8.288475036621094,
          "volume": 2226893.5
        },
        {
          "date": "2026-05-22",
          "open": 8.299710273742676,
          "high": 8.654104232788086,
          "low": 8.255992889404297,
          "close": 8.481829643249512,
          "volume": 3109135.75
        }
      ],
      "prediction_logic": "事件已引发稀土板块短期情绪共振，北方稀土（600111）及中国稀土（000831）当前涨幅（+2.15% / +1.85%）反映了部分市场预期。综合估值与基本面，建议关注北方稀土（目标价28.00元，对应空间+5.66%）及格林美（目标价10.50元，对应空间+7.14%）。"
    }
  }
}